Workbook

Sheet Totales
B11: TOTALES
B12: Editorial | D12: Subtotal | E12: Dto | F12: Total
B13: Ivrea | D13: =Ivrea!E3145 -> 0 | E13: 0.35 | F13: =D13*(100%-E13) -> 0
B14: Ovni Press | D14: =Ovnipress!F779 -> 0 | E14: 0.3 | F14: =D14*(100%-E14) -> 0
B15: Panini y utopia | D15: ='Panini-Utopia'!F1933 -> 0 | E15: 0.2 | F15: =D15*(100%-E15) -> 0
B16: Penguin | D16: =Penguin!F652 -> 0 | E16: 0.35 | F16: =D16*(100%-E16) -> 0
B17: Planeta | D17: =Planeta!E564 -> 0 | E17: 0.35 | F17: =D17*(100%-E17) -> 0
B18: Pop Fiction | D18: ='Deux-PopFiction'!G210 -> 0 | E18: 0.4 | F18: =D18*(100%-E18) -> 0
B19: Hotel de las Ideas | D19: ='Hotel de las Ideas'!F135 -> 0 | E19: 0.4 | F19: =D19*(100%-E19) -> 0
B20: V&R | D20: ='V&R'!F681 -> 0 | E20: 0.35 | F20: =D20*(100%-E20) -> 0
B21: Otras | D21: =Otras!F635 -> 0 | E21: 0.35 | F21: =D21*(100%-E21) -> 0
B22: Merchandising | D22: =Merchandising!E138 -> 0 | F22: =D22*(100%-E22) -> 0
B23: Total | F23: =SUM(F13:F22) -> 0
B26: TITULOS EN ROJO AGOTADOS TEMPORALMENTE, FAVOR DE NO PEDIR.

Sheet Ivrea
A8: POR FAVOR COMPLETAR LAS REEDICIONES ARRIBA. NO EN EL FONDO!
A9: NOVEDADES
A10: TITULO | B10: EAN | C10: PRECIO TAPA | D10: CANTIDAD | E10: Subtotal
A11: FRIEREN -MÁS ALLÁ DEL FINAL- PRELUDIO | B11: ISBN A CONFIRMAR | C11: 12500 | D11: 8 | E11: =Ivrea!$D11*C11 -> 0
A12: MOONLIGHT MILE -RERECORD EDITION- 01 | B12: ISBN A CONFIRMAR | C12: 27000 | D12: 1 | E12: =Ivrea!$D12*C12 -> 0
A13: SOLO LEVELING 14 - SIDE STORY 01 | B13: ISBN A CONFIRMAR | C13: 27900 | D13: 3 | E13: =Ivrea!$D13*C13 -> 0
A14: DANDADAN 22 | B14: ISBN A CONFIRMAR | C14: 9500 | D14: 13 | E14: =Ivrea!$D14*C14 -> 0
A15: CHAINSAW MAN 23 | B15: ISBN A CONFIRMAR | C15: 9500 | D15: 18 | E15: =Ivrea!$D15*C15 -> 0
A16: EL REY BESTIA Y LAS HIERBAS MEDICINALES 02 | B16: ISBN A CONFIRMAR | C16: 10500 | D16: 1 | E16: =Ivrea!$D16*C16 -> 0
A17: EVANGELION: ANIMA 04 | B17: ISBN A CONFIRMAR | C17: 17900 | D17: 2 | E17: =Ivrea!$D17*C17 -> 0
A18: YAKUZA LOVER 09 | B18: ISBN A CONFIRMAR | C18: 9500 | E18: =Ivrea!$D18*C18 -> 0
A19: YAKUZA LOVER 10 | B19: ISBN A CONFIRMAR | C19: 9500 | E19: =Ivrea!$D19*C19 -> 0
A20: YAKUZA LOVER 11 | B20: ISBN A CONFIRMAR | C20: 9500 | E20: =Ivrea!$D20*C20 -> 0
A21: YAKUZA LOVER 12 | B21: ISBN A CONFIRMAR | C21: 9500 | E21: =Ivrea!$D21*C21 -> 0
A22: AGENCIA DEL AMOR 02 | B22: ISBN A CONFIRMAR | C22: 10500 | D22: 7 | E22: =Ivrea!$D22*C22 -> 0
A23: GRAND BLUE 10 | B23: ISBN A CONFIRMAR | C23: 10500 | D23: 3 | E23: =Ivrea!$D23*C23 -> 0
A24: GRAND BLUE 11 | B24: ISBN A CONFIRMAR | C24: 10500 | D24: 3 | E24: =Ivrea!$D24*C24 -> 0
A25: BAKI THE GRAPPLER KANZENBAN 14 | B25: ISBN A CONFIRMAR | C25: 25500 | E25: =Ivrea!$D25*C25 -> 0
A26: BAKI THE GRAPPLER KANZENBAN 15 | B26: ISBN A CONFIRMAR | C26: 25500 | E26: =Ivrea!$D26*C26 -> 0
A27: D.N.ANGEL KANZENBAN 09 | B27: ISBN A CONFIRMAR | C27: 25500 | E27: =Ivrea!$D27*C27 -> 0
A28: D.N.ANGEL KANZENBAN 10 | B28: ISBN A CONFIRMAR | C28: 25500 | E28: =Ivrea!$D28*C28 -> 0
A29: GACHIAKUTA 14 | B29: ISBN A CONFIRMAR | C29: 9500 | D29: 8 | E29: =Ivrea!$D29*C29 -> 0
A30: REIMPRESIONES
A31: DEMON SLAYER - KIMETSU NO YAIBA: ARTBOOK | B31: 9788410475304 | C31: 33500 | D31: 5 | E31: =Ivrea!$D31*C31 -> 0
A32: SOLO LEVELING 02 | B32: 9788419383846 | C32: 27900 | D32: 1 | E32: =Ivrea!$D32*C32 -> 0
A33: MIS 100 NOVIAS QUE ME QUIEREN MUCHO MUCHO 01 | B33: 9791387500405 | C33: 10500 | D33: 2 | E33: =Ivrea!$D33*C33 -> 0
A34: MANGAS EN CURSO
A35: AGENCIA DEL AMOR 01 | B35: 9791388249303 | C35: 10500 | E35: =Ivrea!$D35*C35 -> 0
A36: ALICE ON BORDER ROAD 01 | B36: 9791387981891 | C36: 17900 | E36: =Ivrea!$D36*C36 -> 0
A37: ALICE ON BORDER ROAD 02 | B37: 9791388104114 | C37: 17900 | E37: =Ivrea!$D37*C37 -> 0
A38: ALICE ON BORDER ROAD 03 | B38: 9791388249389 | C38: 17900 | E38: =Ivrea!$D38*C38 -> 0
A39: AO ASHI 01 | B39: 9791388178504 | C39: 18900 | E39: =Ivrea!$D39*C39 -> 0
A40: ASADORA! 01 | B40: 9791387892609 | C40: 10500 | E40: =Ivrea!$D40*C40 -> 0
A41: ASADORA! 02 | B41: 9791387981853 | C41: 10500 | E41: =Ivrea!$D41*C41 -> 0
A42: ASADORA! 03 | B42: 9791388104824 | C42: 10500 | E42: =Ivrea!$D42*C42 -> 0
A43: ASADORA! 04 | B43: 9791388249471 | C43: 10500 | E43: =Ivrea!$D43*C43 -> 0
A44: ATELIER OF WITCH HAT 01 | B44: 9788418061899 | C44: 10500 | E44: =Ivrea!$D44*C44 -> 0
A45: ATELIER OF WITCH HAT 02 | B45: 9788418172755 | C45: 10500 | D45: 1 | E45: =Ivrea!$D45*C45 -> 0
A46: ATELIER OF WITCH HAT 03 | B46: 9788418271328 | C46: 10500 | D46: 1 | E46: =Ivrea!$D46*C46 -> 0
A47: ATELIER OF WITCH HAT 04 | B47: 9788418450846 | C47: 10500 | E47: =Ivrea!$D47*C47 -> 0
A48: ATELIER OF WITCH HAT 05 | B48: 9788418562907 | C48: 10500 | E48: =Ivrea!$D48*C48 -> 0
A49: ATELIER OF WITCH HAT 06 | B49: 9788418751240 | C49: 10500 | E49: =Ivrea!$D49*C49 -> 0
A50: ATELIER OF WITCH HAT 07 | B50: 9788418837371 | C50: 10500 | E50: =Ivrea!$D50*C50 -> 0
A51: ATELIER OF WITCH HAT 08 | B51: 9788419096616 | C51: 10500 | E51: =Ivrea!$D51*C51 -> 0
A52: ATELIER OF WITCH HAT 09 | B52: 9788419306401 | C52: 10500 | E52: =Ivrea!$D52*C52 -> 0
A53: ATELIER OF WITCH HAT 10 | B53: 9788419451996 | C53: 10500 | E53: =Ivrea!$D53*C53 -> 0
A54: ATELIER OF WITCH HAT 11 | B54: 9788419869234 | C54: 10500 | E54: =Ivrea!$D54*C54 -> 0
A55: ATELIER OF WITCH HAT 12 | B55: 9788410113084 | C55: 10500 | E55: =Ivrea!$D55*C55 -> 0
A56: ATELIER OF WITCH HAT 13 | B56: 9791387500078 | C56: 10500 | E56: =Ivrea!$D56*C56 -> 0
A57: ATELIER OF WITCH HAT 14 | B57: 9791387892470 | C57: 10500 | E57: =Ivrea!$D57*C57 -> 0
A58: ATELIER OF WITCH HAT 15 | B58: 9791388249730 | C58: 10500 | E58: =Ivrea!$D58*C58 -> 0
... A69: BAKI THE GRAPPLER KANZENBAN 11 | B69: 9791387892982 | C69: 25500 | E69: =Ivrea!$D69*C69 -> 0
A70: BAKI THE GRAPPLER KANZENBAN 12 | B70: 9791388024979 | C70: 25500 | E70: =Ivrea!$D70*C70 -> 0
A71: BAKI THE GRAPPLER KANZENBAN 13 | B71: 9791388104732 | C71: 25500 | E71: =Ivrea!$D71*C71 -> 0
A72: BASTARDO 01 | B72: 9791388178269 | C72: 35000 | E72: =Ivrea!$D72*C72 -> 0
A73: BLACK CLOVER 01 | B73: 9788418172687 | C73: 9500 | E73: =Ivrea!$D73*C73 -> 0
A74: BLACK CLOVER 02 | B74: 9788418271007 | C74: 9500 | E74: =Ivrea!$D74*C74 -> 0
A75: BLACK CLOVER 03 | B75: 9788418271311 | C75: 9500 | E75: =Ivrea!$D75*C75 -> 0
A76: BLACK CLOVER 04 | B76: 9788418271571 | C76: 9500 | E76: =Ivrea!$D76*C76 -> 0
A77: BLACK CLOVER 05 | B77: 9788418271915 | C77: 9500 | E77: =Ivrea!$D77*C77 -> 0
A78: BLACK CLOVER 06 | B78: 9788418450723 | C78: 9500 | E78: =Ivrea!$D78*C78 -> 0
A79: BLACK CLOVER 07 | B79: 9788418562327 | C79: 9500 | E79: =Ivrea!$D79*C79 -> 0
A80: BLACK CLOVER 08 | B80: 9788418562921 | C80: 9500 | E80: =Ivrea!$D80*C80 -> 0
A81: BLACK CLOVER 09 | B81: 9788418645372 | C81: 9500 | E81: =Ivrea!$D81*C81 -> 0
A82: BLACK CLOVER 10 | B82: 9788418645969 | C82: 9500 | E82: =Ivrea!$D82*C82 -> 0
... A108: BLACK CLOVER 36 | B108: 9791388024498 | C108: 9500 | E108: =Ivrea!$D108*C108 -> 0
A109: BLACK CLOVER 37 | B109: 9791388178528 | C109: 9500 | E109: =Ivrea!$D109*C109 -> 0
A110: BLEACH EDICIÓN REMIX 01 | B110: 9788419451859 | C110: 23500 | E110: =Ivrea!$D110*C110 -> 0
A111: BLEACH EDICIÓN REMIX 02 | B111: 9788419730381 | C111: 23500 | E111: =Ivrea!$D111*C111 -> 0
A112: BLEACH EDICIÓN REMIX 03 | B112: 9788419869227 | C112: 23500 | E112: =Ivrea!$D112*C112 -> 0
A113: BLEACH EDICIÓN REMIX 04 | B113: 9788410007178 | C113: 23500 | E113: =Ivrea!$D113*C113 -> 0
A114: BLEACH EDICIÓN REMIX 05 | B114: 9788410113152 | C114: 23500 | E114: =Ivrea!$D114*C114 -> 0
A115: BLEACH EDICIÓN REMIX 06 | B115: 9788410213111 | C115: 23500 | E115: =Ivrea!$D115*C115 -> 0
A116: BLEACH EDICIÓN REMIX 07 | B116: 9788410258419 | C116: 23500 | E116: =Ivrea!$D116*C116 -> 0
A117: BLEACH EDICIÓN REMIX 08 | B117: 9788410388086 | C117: 23500 | E117: =Ivrea!$D117*C117 -> 0
A118: BLEACH EDICIÓN REMIX 09 | B118: 9791387500528 | C118: 23500 | D118: 1 | E118: =Ivrea!$D118*C118 -> 0
A119: BLEACH EDICIÓN REMIX 10 | B119: 9791387619275 | C119: 23500 | E119: =Ivrea!$D119*C119 -> 0
A120: BLEACH EDICIÓN REMIX 11 | B120: 9791387784195 | C120: 23500 | E120: =Ivrea!$D120*C120 -> 0
A121: BLEACH EDICIÓN REMIX 12 | B121: 9791387836696 | C121: 23500 | E121: =(C121*D121) -> 0
A122: BLEACH EDICIÓN REMIX 13 | B122: 9791387981181 | C122: 23500 | E122: =Ivrea!$D122*C122 -> 0
A123: BLEACH EDICIÓN REMIX 14 | B123: 9791388024436 | C123: 23500 | E123: =Ivrea!$D123*C123 -> 0
A124: BLEACH EDICIÓN REMIX 15 | B124: 9791388178016 | C124: 23500 | E124: =Ivrea!$D124*C124 -> 0
A125: BLUE BOX 01 | B125: 9788410007055 | C125: 9500 | E125: =Ivrea!$D125*C125 -> 0
A126: BLUE BOX 02 | B126: 9788410113145 | C126: 9500 | E126: =Ivrea!$D126*C126 -> 0
A127: BLUE BOX 03 | B127: 9788410213371 | C127: 9500 | E127: =Ivrea!$D127*C127 -> 0
A128: BLUE BOX 04 | B128: 9788410258549 | C128: 9500 | E128: =Ivrea!$D128*C128 -> 0
A129: BLUE BOX 05 | B129: 9788410388628 | C129: 9500 | E129: =Ivrea!$D129*C129 -> 0
A130: BLUE BOX 06 | B130: 9791387784386 | C130: 9500 | E130: =Ivrea!$D130*C130 -> 0
A131: BLUE BOX 07 | B131: 9791387892449 | C131: 9500 | E131: =Ivrea!$D131*C131 -> 0
A132: BLUE BOX 08 | B132: 9791387981013 | C132: 9500 | E132: =Ivrea!$D132*C132 -> 0
A133: BLUE BOX 09 | B133: 9791388024078 | C133: 9500 | E133: =Ivrea!$D133*C133 -> 0
A134: BLUE BOX 10 | B134: 9791388104077 | C134: 9500 | E134: =Ivrea!$D134*C134 -> 0
A135: BLUE BOX 11 | B135: 9791388104893 | C135: 9500 | E135: =Ivrea!$D135*C135 -> 0
A136: BLUE BOX 12 | B136: 9791388104909 | C136: 9500 | E136: =Ivrea!$D136*C136 -> 0
A137: BLUE EXORCIST 01 | B137: 9788415922285 | C137: 8500 | E137: =Ivrea!$D137*C137 -> 0
A138: BLUE EXORCIST 02 | B138: 9788415922568 | C138: 8500 | E138: =Ivrea!$D138*C138 -> 0
A139: BLUE EXORCIST 03 | B139: 9788415922797 | C139: 8500 | E139: =Ivrea!$D139*C139 -> 0
A140: BLUE EXORCIST 04 | B140: 9788416040575 | C140: 8500 | E140: =Ivrea!$D140*C140 -> 0
A141: BLUE EXORCIST 05 | B141: 9788415922278 | C141: 8500 | E141: =Ivrea!$D141*C141 -> 0
A142: BLUE EXORCIST 06 | B142: 9788415922278 | C142: 8500 | E142: =Ivrea!$D142*C142 -> 0
...

Sheet Ovnipress
A13: NOVEDADES
A14: Cant. de pág | B14: Título | C14: ISBN | D14: PVP | E14: CANT | F14: subtotal
A15: 128 | B15: DC - BLACK LABEL - DOOM PATROL: FLEX MENTALLO - EDICIÓN ABSOLUTA | C15: 978-987-819-535-3 | D15: 20000 | E15: 1 | F15: =E15*D15 -> 0
A16: 292 | B16: DC - BLACK LABEL - DOOM PATROL: LIBRO 1 (2da Edición) | C16: 978-987-819-533-9 | D16: 32000 | E16: 1 | F16: =E16*D16 -> 0
A17: 436 | B17: DC - FLASH vol. 3: CONFLICTO ELEMENTAL | C17: 978-987-819-617-6 | D17: 42000 | F17: =E17*D17 -> 0
A18: 352 | B18: MOZTROS - RENACIMIENTO DEL UNIVERSO VALIANT | C18: 978-84-10463-55-4 | D18: 28000 | E18: 1 | F18: =E18*D18 -> 0
C19: ISBN | D19: PVP | F19: subtotal
A20: 232 | B20: DC - BLACK LABEL - HELLBLAZER: ABRÁZAME (y otras historias) | C20: 978-987-819-615-2 | D20: 28000 | F20: =E20*D20 -> 0
A21: 208 | B21: DC - BLACK LABEL - SWAMP THING Vol. 01 (4ta Edición) | C21: 978-987-819-610-7 | D21: 28000 | F21: =E21*D21 -> 0
A22: 216 | B22: DC - LA NUEVA HISTORIA DEL UNIVERSO DC | C22: 978-987-819-618-3 | D22: 32000 | F22: =E22*D22 -> 0
A23: 144 | B23: MOZTROS - TEENAGE MUTANT NINJA TURTLES : ESPECIAL 40 ANIVERSARIO | C23: 978-84-10463-97-4 | D23: 26000 | F23: =E23*D23 -> 0
A24: 192 | B24: DC - ABSOLUTE BATMAN Vol. 1 (4ra Edicion) | C24: 978-987-819-565-0 | D24: 28000 | F24: =E24*D24 -> 0
A25: 208 | B25: DC - ABSOLUTE BATMAN Vol. 2 | C25: 978-987-819-560-5 | D25: 28000 | F25: =E25*D25 -> 0
A26: 168 | B26: DC - ABSOLUTE FLASH VOL 01 | C26: 978-987-819-509-4 | D26: 26000 | F26: =E26*D26 -> 0
A27: 176 | B27: DC - ABSOLUTE GREEN LANTERN Vol. 1 | C27: 978-987-819-614-5 | D27: 26000 | F27: =E27*D27 -> 0
A28: 160 | B28: DC - ABSOLUTE MARTIAN MANHUNTER Vol. 1 | C28: 978-987-819-519-3 | D28: 28000 | F28: =E28*D28 -> 0
A29: 168 | B29: DC - ABSOLUTE SUPERMAN Vol. 01 (2da edición) | C29: 978-987-819-525-4 | D29: 26000 | F29: =E29*D29 -> 0
A30: 208 | B30: DC - ABSOLUTE SUPERMAN Vol. 02 | C30: 978-987-819-602-2 | D30: 26000 | F30: =E30*D30 -> 0
A31: 184 | B31: DC - ABSOLUTE WONDER WOMAN VOL 01 | C31: 978-987-819-526-1 | D31: 26000 | F31: =E31*D31 -> 0
... A128: 296 | B128: DC - BATMAN: NO MAN'S LAND Vol. 3 - CATACLISMO (PARTE 1) | C128: 978-987-819-546-9 | D128: 30000 | F128: =E128*D128 -> 0
A129: 308 | B129: DC - BATMAN: NO MAN'S LAND Vol. 4 - CATACLISMO (PARTE 2) | C129: 978-987-819-593-3 | D129: 30000 | E129: 1 | F129: =E129*D129 -> 0
A130: 296 | B130: DC - BATMAN: PATRONES OSCUROS | C130: 978-987-819-601-5 | D130: 35000 | F130: =E130*D130 -> 0
A131: 136 | B131: DC - BATMAN: PRESA | C131: 978-987-819-241-3 | D131: 18000 | F131: =E131*D131 -> 0
A132: 200 | B132: DC - BATMAN: PRISIONES OSCURAS | C132: 978-987-819-387-8 | D132: 25000 | F132: =E132*D132 -> 0
A133: 312 | B133: DC - BATMAN: PRÓDIGO (EPÍLOGO A LA CAÍDA DEL CABALLERO) | C133: 978-987-819-295-6 | D133: 28000 | F133: =E133*D133 -> 0
A134: 136 | B134: DC - BATMAN: REFLEJOS | C134: 978-987-819-386-1 | D134: 20000 | F134: =E134*D134 -> 0
A135: 160 | B135: DC - BATMAN: RECUPERANDO LA CORDURA | C135: 978-987-819-544-5 | D135: 26000 | F135: =E135*D135 -> 0
A136: 136 | B136: DC - BATMAN: ROSTROS | C136: 978-987-819-284-0 | D136: 20000 | F136: =E136*D136 -> 0
A137: 188 | B137: DC - BATMAN: SANTUARIO | C137: 978-987-819-421-9 | D137: 22000 | F137: =E137*D137 -> 0
A138: 144 | B138: DC - BATMAN: SHAMAN | C138: 978-987-819-231-4 | D138: 22000 | F138: =E138*D138 -> 0
A139: 212 | B139: DC - BATMAN: TROIKA | C139: 978-987-819-346-5 | D139: 28000 | F139: =E139*D139 -> 0
A140: 288 | B140: DC - BATMAN: VAMPIRO | C140: 978-987-819-257-4 | D140: 30000 | F140: =E140*D140 -> 0
A141: 136 | B141: DC - BATMAN: VENENO | C141: 978-987-819-493-6 | D141: 20000 | F141: =E141*D141 -> 0
... A254: 218 | B254: DC - ECC - ESCUADRÓN SUICIDA Vol. 1 | C254: 978-84-17401-84-9 | D254: 22000 | F254: =E254*D254 -> 0
A255: 144 | B255: DC - ECC - FLASH Vol. 2 | C255: 978-84-17316-80-8 | F255: =E255*D255 -> 0
A256: 168 | B256: DC - ECC - HARLEY QUINN Vol. 1 | C256: 978-84-17106-65-2 | D256: 26000 | F256: =E256*D256 -> 0
A257: 168 | B257: DC - ECC - LIGA DE LA JUSTICIA Vol. 01 | C257: 978-84-17106-66-9 | D257: 23000 | F257: =E257*D257 -> 0
A258: 144 | B258: DC - ECC - LIGA DE LA JUSTICIA Vol. 02 | C258: 978-84-17316-85-3 | D258: 22000 | F258: =E258*D258 -> 0
A259: 120 | B259: DC - ECC - SUPERHIJOS Vol. 01 CUANDO SEA MAYOR… | C259: 978-84-17316-91-4 | D259: 22000 | F259: =E259*D259 -> 0
A260: 208 | B260: DC - ECC - SUPERMAN Vol. 02 | C260: 978-84-17316-74-7 | D260: 21000 | F260: =E260*D260 -> 0
A261: 144 | B261: DC - ECC - TRINIDAD: MEJOR JUNTOS Vol. 01 | C261: 978-84-17316-93-8 | D261: 18000 | F261: =E261*D261 -> 0
A262: 144 | B262: DC - ECC - WONDER WOMAN: TIERRA UNO | C262: 978-84-17147-48-8 | D262: 18000 | F262: =E262*D262 -> 0
A263: 160 | B263: DC - EL DESAFÍO DE LOS SUPERHIJOS | C263: 978-987-724-854-8 | D263: 32000 | F263: =E263*D263 -> 0
A264: 248 | B264: DC - EL HOMBRE DE ACERO | C264: 978-987-724-670-4 | D264: 26000 | F264: =E264*D264 -> 0
A265: 144 | B265: DC - EL JOKER Vol. 02 | C265: 978-987-819-030-3 | D265: 22000 | F265: =E265*D265 -> 0
A266: 160 | B266: DC - EL JOKER Vol. 03 | C266: 978-987-819-156-0 | D266: 22000 | F266: =E266*D266 -> 0
A267: 248 | B267: DC - ESENCIALES DC - ¡INVASIÓN! | C267: 978-987-819-305-2 | D267: 28000 | F267: =E267*D267 -> 0
... A659: 112 | B659: MOZTROS - MIGHTY MORPHIN VOL. 03 | C659: 978-84-19903-75-4 | D659: 29000 | F659: =E659*D659 -> 0
A660: 216 | B660: MOZTROS - MIGHTY MORPHIN VOL. 04 | C660: 978-84-19903-96-9 | D660: 33000 | E660: 1 | F660: =E660*D660 -> 0
A661: 224 | B661: MOZTROS - MIGHTY MORPHIN POWER RANGERS Vol. 01 (REINGRESO) | C661: 978-84-18955-01-3 | D661: 29000 | F661: =E661*D661 -> 0
A662: 200 | B662: MOZTROS - MIGHTY MORPHIN POWER RANGERS Vol. 02 (REINGRESO) | C662: 978-84-18955-02-0 | D662: 29000 | F662: =E662*D662 -> 0
A663: 200 | B663: MOZTROS - MIGHTY MORPHIN POWER RANGERS Vol. 3 (REPOSICIÓN) | C663: 978-84-18955-34-1 | D663: 29000 | F663: =E663*D663 -> 0
A664: 240 | B664: MOZTROS - MIGHTY MORPHIN POWER RANGERS Vol. 4 (REPOSICIÓN ) | C664: 978-84-18955-48-8 | D664: 29000 | F664: =E664*D664 -> 0
A665: 224 | B665: MOZTROS - MIGHTY MORPHIN POWER RANGERS Vol. 5 (Reingreso) | C665: 978-84-18955-59-4 | D665: 29000 | F665: =E665*D665 -> 0
A666: 320 | B666: MOZTROS - MIGHTY MORPHIN POWER RANGERS Vol. 6 | C666: 978-84-18955-67-9 | D666: 29000 | F666: =E666*D666 -> 0
A667: 224 | B667: MOZTROS - MIGHTY MORPHIN POWER RANGERS Vol. 7 (FINAL) | C667: 978-84-19903-18-1 | D667: 29000 | F667: =E667*D667 -> 0
A668: 192 | B668: MOZTROS - MIGHTY MOPHIN POWER RANGERS: PINK | C668: 978-84-19903-12-9 | D668: 29000 | F668: =E668*D668 -> 0
A669: 144 | B669: MOZTROS - MMPR VS LAS TORTUGAS NINJA Vol. 02 | C669: 978-84-19903-67-9 | D669: 29000 | F669: =E669*D669 -> 0
A670: 112 | B670: MOZTROS - MONEY SHOT Vol. 02 | C670: 978-841-899-513-6 | D670: 29000 | F670: =E670*D670 -> 0
A671: 120 | B671: MOZTROS - MONEY SHOT Vol. 03 | C671: 978-84-18955-29-7 | D671: 29000 | F671: =E671*D671 -> 0
A672: 128 | B672: MOZTROS - MONSTRUOS DE UNIVERSAL: DRÁCULA | C672: 978-84-19903-92-1 | D672: 28000 | F672: =E672*D672 -> 0
... A718: 112 | B718: MOZTROS - FAR SOUTH | C718: 978-84-18955-97-6 | D718: 32000 | F718: =E718*D718 -> 0
A719: 160 | B719: MOZTROS - TRANSFORMERS VOL 1 | C719: 978-84-19903-77-8 | F719: =E719*D719 -> 0
A720: 136 | B720: MOZTROS - TRANSFORMERS VOL 2 | C720: 978-84-10463-31-8 | F720: =E720*D720 -> 0
A721: 160 | B721: MOZTROS - TRANSFORMERS VOL 3 | C721: 978-84-10463-92-9 | D721: 25000 | F721: =E721*D721 -> 0
A722: 160 | B722: MOZTROS - UNIVERSO POWER RANGERS | C722: 978-84-19903-82-2 | D722: 25000 | F722: =E722*D722 -> 0
A723: 128 | B723: MOZTROS - UNIVERSO TRANSFORMERS: COMANDANTE COBRA | C723: 978-84-10463-64-6 | D723: 25000 | F723: =E723*D723 -> 0
A724: 128 | B724: MOZTROS - UNIVERSO TRANSFORMERS: DESTRO | C724: 978-841-0463-936 | D724: 25000 | F724: =E724*D724 -> 0
A725: 128 | B725: MOZTROS - UNIVERSO TRANSFORMERS: DUKE | C725: 978-84-10463-04-2 | F725: =E725*D725 -> 0
A726: 144 | B726: MOZTROS - UNIVERSO TRANSFORMERS: G.I. JOE Vol 01 | C726: 978-84-10463-94-3 | D726: 25000 | F726: =E726*D726 -> 0
A727: 128 | B727: MOZTROS - UNIVERSO TRANSFORMERS: SCARLETT | C727: 978-841-046-365-3 | F727: =E727*D727 -> 0
A728: 144 | B728: MOZTROS - UNIVERSO TRANSFORMERS: VOID RIVALS 01 | C728: 978-84-19903-71-6 | D728: 25000 | F728: =E728*D728 -> 0
A729: 144 | B729: MOZTROS - UNIVERSO TRANSFORMERS: VOID RIVALS 02 | C729: 978-84-10463-90-5 | D729: 25000 | F729: =E729*D729 -> 0
A730: 144 | B730: MOZTROS - UNIVERSO TRANSFORMERS: VOID RIVALS 03 | C730: 978-84-10463-91-2 | D730: 25000 | F730: =E730*D730 -> 0
A731: 224 | B731: MOZTROS - VANISH - PACK (Vol. 1 + Vol. 2) | C731: 978-84-10463-68-4 | D731: 35000 | F731: =E731*D731 -> 0
A732: 136 | B732: MOZTROS - X-O MANOWAR: INVICTO | C732: 978-84-19903-46-4 | D732: 29000 | F732: =E732*D732 -> 0
A733: 144 | B733: MOZTROS - X-O MANOWAR Vol. 01 | C733: 978-84-18995-19-8 | D733: 29000 | F733: =E733*D733 -> 0
A734: 96 | B734: MOZTROS - X-O MANOWAR Vol. 02 | C734: 978-841-895-538-9 | D734: 29000 | F734: =E734*D734 -> 0
A735: 256 | B735: MOZTROS - ZOMBIES VS ROBOTS CLASSICS (EDICIÓN METAL) | C735: 978-84-18955-78-5 | D735: 24000 | F735: =E735*D735 -> 0
A736: 132 | B736: MARVEL - COLECCIÓN SPIDER-MAN UNIVERSO ARAÑA 05: SPIDER VERSE: SEGUNDA PARTE | C736: 978-987-724-902-6 | D736: 16000 | F736: =E736*D736 -> 0
A737: 128 | B737: MARVEL - COLECCIÓN SPIDER-MAN UNIVERSO ARAÑA 18: VENOM: PRIMER ANFITRIÓN | C737: 978-987-819-059-4 | D737: 16000 | F737: =E737*D737 -> 0
A738: 120 | B738: MARVEL - COLECCIÓN SPIDER-MAN UNIVERSO ARAÑA 19: ISLA ARAÑA | C738: 978-987-819-060-0 | D738: 16000 | F738: =E738*D738 -> 0
A739: 128 | B739: MARVEL - COLECCIÓN SPIDER-MAN UNIVERSO ARAÑA 20: SPIDER-GWEN: LA MÁS BUSCADA | C739: 978-987-819-061-7 | D739: 16000 | F739: =E739*D739 -> 0
... A778: 152 | B778: DH - O.D.I.P.: SER HUMANO | C778: 978-987-724-379-6 | D778: 15000 | F778: =E778*D778 -> 0
B779: SUBTOTAL | F779: =SUM(F1:F778) -> 0

Sheet Panini-Utopia
A8: NOVEDADES
A9: Código | B9: Titulo | C9: Isbn | D9: Precio en ARS | E9: Cant. | F9: Subtotal | G9: Columna1
B10: **PANINI MANGA **
B11: MARVEL FORTNITE CONFLICTO CERO 1 | F11: =E11*D11 -> 0
B12: MARVEL FORTNITE CONFLICTO CERO 5 | F12: =E12*D12 -> 0
A13: PCA40MADE01 | B13: 40 MADE NI SHITAI 10 NO KOTO 01 | C13: 9786075786834 | D13: 13000 | F13: =E13*D13 -> 0
A14: PCAAFTGOD01 | B14: AFTER GOD 01 | C14: 9786075820828 | D14: 12000 | F14: =E14*D14 -> 0
A15: PCAAFTGOD02 | B15: AFTER GOD 02 | C15: 9786075822570 | D15: 12000 | F15: =E15*D15 -> 0
A16: PCAAFTGOD03 | B16: AFTER GOD 03 | C16: 9786075823386 | D16: 12000 | F16: =E16*D16 -> 0
A17: PCAAFTGOD04 | B17: AFTER GOD 04 | C17: 9786075825724 | D17: 12000 | F17: =E17*D17 -> 0
A18: PCAAFTGOD05 | B18: AFTER GOD 05 | C18: 9786075828114 | D18: 12000 | F18: =E18*D18 -> 0
A19: PCAAFTGOD06 | B19: AFTER GOD 06 | C19: 9786075829685 | D19: 12000 | F19: =E19*D19 -> 0
A20: PCAAFTGOD07 | B20: AFTER GOD 07 | C20: 9786076382394 | D20: 12000 | F20: =E20*D20 -> 0
A21: PCAQAADE001 | B21: ALL OF US ARE DEAD 01 | C21: 9786076384664 | D21: 27000 | F21: =E21*D21 -> 0
A22: PCAAUNIKI01 | B22: ALL YOU NEED IS KILL 01 | C22: 9786075280264 | D22: 10500 | F22: =E22*D22 -> 0
A23: PCAAUNIKI02 | B23: ALL YOU NEED IS KILL 02 (ULTIMO TOMO) | C23: 9786075280769 | D23: 10500 | F23: =E23*D23 -> 0
A24: PCAASCLAS02 | B24: ASSASSINATION CLASSROOM 02 | C24: 9786075280554 | D24: 10500 | F24: =E24*D24 -> 0
... A118: PCABERSER41 | B118: BERSERK 41 | C118: 9786076360484 | D118: 13500 | F118: =E118*D118 -> 0
A119: PCABERSEV41 | B119: BERSERK 41 VARIANTE | C119: 7503041492610 | F119: =E119*D119 -> 0
A120: PCABERSER42 | B120: BERSERK 42 | C120: 9786075789613 | D120: 13500 | F120: =E120*D120 -> 0
A121: PCAQMBER042 | B121: BERSERK 42 TAROT EDITION | C121: 9786075823645 | F121: =E121*D121 -> 0
A122: PCABINTOU01 | B122: BLOOM INTO YOU 01 | C122: 9786075685267 | D122: 11000 | F122: =E122*D122 -> 0
A123: PCABINTOU02 | B123: BLOOM INTO YOU 02 | C123: 9786075685656 | D123: 11000 | F123: =E123*D123 -> 0
A124: PCABINTOU03 | B124: BLOOM INTO YOU 03 | C124: 9786075686189 | D124: 11000 | F124: =E124*D124 -> 0
A125: PCABINTOU04 | B125: BLOOM INTO YOU 04 | C125: 9786075686752 | D125: 11000 | F125: =E125*D125 -> 0
A126: PCABINTOU05 | B126: BLOOM INTO YOU 05 | C126: 9786075687285 | D126: 11000 | F126: =E126*D126 -> 0
A127: PCABINTOU06 | B127: BLOOM INTO YOU 06 | C127: 9786075687728 | D127: 11000 | F127: =E127*D127 -> 0
A128: PCABINTOU07 | B128: BLOOM INTO YOU 07 | C128: 9786075688633 | D128: 11000 | F128: =E128*D128 -> 0
A129: PCABINTOU08 | B129: BLOOM INTO YOU 08 (ULTIMO TOMO) | C129: 9786075689395 | D129: 11000 | F129: =E129*D129 -> 0
A130: PCABLUPER01 | B130: BLUE PERIOD 01 | C130: 9786076360446 | D130: 12000 | F130: =E130*D130 -> 0
A131: PCABLUPER02 | B131: BLUE PERIOD 02 | C131: 9786076361016 | D131: 12000 | F131: =E131*D131 -> 0
A132: PCABLUPER03 | B132: BLUE PERIOD 03 | C132: 9786076361566 | D132: 12000 | F132: =E132*D132 -> 0
A133: PCABLUPER04 | B133: BLUE PERIOD 04 | C133: 9786076362549 | D133: 12000 | F133: =E133*D133 -> 0
... A166: PCAIBOBL002 | B166: BORUTO TWO BLUE VORTEX 02 | C166: 9786075827032 | D166: 12000 | F166: =E166*D166 -> 0
A167: PCAWOTAKOPK | B167: BOX SET WOTAKOI TOMOS 01 AL 11 (COMPLETO) | C167: 7503036808525 | F167: =E167*D167 -> 0
A168: PCACLAYMO01 | B168: CLAYMORE 01 | C168: 9786076345764 | D168: 12000 | F168: =E168*D168 -> 0
A169: PCACLAYMO03 | B169: CLAYMORE 03 | C169: 9786076347027 | D169: 12000 | F169: =E169*D169 -> 0
A170: PCACLAYMO04 | B170: CLAYMORE 04 | C170: 9786076347218 | D170: 12000 | F170: =E170*D170 -> 0
A171: PCACLAYMO05 | B171: CLAYMORE 05 | C171: 9786076347225 | D171: 12000 | F171: =E171*D171 -> 0
A172: PCACLAYMO06 | B172: CLAYMORE 06 | C172: 9786076347812 | D172: 12000 | F172: =E172*D172 -> 0
A173: PCACLAYMO09 | B173: CLAYMORE 09 | C173: 9786076348437 | D173: 12000 | F173: =E173*D173 -> 0
A174: PCACLAYMO10 | B174: CLAYMORE 10 | C174: 9786075684390 | D174: 12000 | F174: =E174*D174 -> 0
A175: PCACLAYMO11 | B175: CLAYMORE 11 | C175: 9786075684819 | D175: 12000 | F175: =E175*D175 -> 0
A176: PCACLAYMO14 | B176: CLAYMORE 14 | C176: 9786075686769 | D176: 12000 | F176: =E176*D176 -> 0
A177: PCACLAYMO16 | B177: CLAYMORE 16 | C177: 9786075687735 | D177: 12000 | F177: =E177*D177 -> 0
A178: PCACLAYMO17 | B178: CLAYMORE 17 | C178: 9786075689005 | D178: 12000 | F178: =E178*D178 -> 0
A179: PCACLAYMO18 | B179: CLAYMORE 18 | C179: 9786075689678 | D179: 12000 | F179: =E179*D179 -> 0
... A409: PCAIARJS001 | B409: JUJUTSU KAISEN 0 MOVIE EDITION LA NOVELA | C409: 9786075789057 | D409: 14500 | F409: =E409*D409 -> 0
A410: PCAJKAISE00 | B410: JUJUTSU KAISEN 00 | C410: 9786075683409 | D410: 13000 | E410: 2 | F410: =E410*D410 -> 0
A411: PCAJKAISE01 | B411: JUJUTSU KAISEN 01 | C411: 9786076349694 | D411: 13000 | E411: 2 | F411: =E411*D411 -> 0
A412: PCAJKAISE02 | B412: JUJUTSU KAISEN 02 | C412: 9786076349953 | D412: 13000 | E412: 2 | F412: =E412*D412 -> 0
A413: PCAJKAISE03 | B413: JUJUTSU KAISEN 03 | C413: 9786075681771 | D413: 13000 | F413: =E413*D413 -> 0 | G413: REINGRESO
A414: PCAJKAISE04 | B414: JUJUTSU KAISEN 04 | C414: 9786075682020 | D414: 13000 | E414: 1 | F414: =E414*D414 -> 0 | G414: REINGRESO
A415: PCAJKAISE05 | B415: JUJUTSU KAISEN 05 | C415: 9786075682846 | D415: 13000 | F415: =E415*D415 -> 0 | G415: REINGRESO
A416: PCAJKAISE06 | B416: JUJUTSU KAISEN 06 | C416: 9786075682853 | D416: 13000 | F416: =E416*D416 -> 0 | G416: REINGRESO
A417: PCAJKAISE07 | B417: JUJUTSU KAISEN 07 | C417: 9786075683140 | D417: 13000 | E417: 1 | F417: =E417*D417 -> 0 | G417: REINGRESO
A418: PCAJKAISE08 | B418: JUJUTSU KAISEN 08 | C418: 9786075683638 | D418: 13000 | E418: 2 | F418: =E418*D418 -> 0
A419: PCAJKAISE09 | B419: JUJUTSU KAISEN 09 | C419: 9786075684369 | D419: 13000 | E419: 1 | F419: =E419*D419 -> 0 | G419: REINGRESO
A420: PCAJKAISE10 | B420: JUJUTSU KAISEN 10 | C420: 9786075684895 | D420: 13000 | E420: 1 | F420: =E420*D420 -> 0 | G420: REINGRESO
A421: PCAJKAISE11 | B421: JUJUTSU KAISEN 11 | C421: 9786075685670 | D421: 13000 | E421: 1 | F421: =E421*D421 -> 0 | G421: REINGRESO
A422: PCAJKAISE12 | B422: JUJUTSU KAISEN 12 | C422: 9786075686097 | D422: 13000 | E422: 1 | F422: =E422*D422 -> 0 | G422: REINGRESO
A423: PCAJKAISE13 | B423: JUJUTSU KAISEN 13 | C423: 9786075686325 | D423: 13000 | E423: 1 | F423: =E423*D423 -> 0 | G423: REINGRESO
A424: PCAJKAISE14 | B424: JUJUTSU KAISEN 14 | C424: 9786075687346 | D424: 13000 | F424: =E424*D424 -> 0
A425: PCAJKAISE15 | B425: JUJUTSU KAISEN 15 | C425: 9786075688985 | D425: 13000 | F425: =E425*D425 -> 0
A426: PCAJKAISE16 | B426: JUJUTSU KAISEN 16 | C426: 9786075689692 | D426: 13000 | F426: =E426*D426 -> 0
A427: PCAJKAISE17 | B427: JUJUTSU KAISEN 17 | C427: 9786075689869 | D427: 13000 | E427: 1 | F427: =E427*D427 -> 0 | G427: REINGRESO
A428: PCAJKAISE18 | B428: JUJUTSU KAISEN 18 | C428: 9786076361139 | D428: 13000 | F428: =E428*D428 -> 0
A429: PCAJKAISE19 | B429: JUJUTSU KAISEN 19 | C429: 9786076363225 | D429: 13000 | F429: =E429*D429 -> 0
A430: PCAJKAISE20 | B430: JUJUTSU KAISEN 20 | C430: 9786076366042 | D430: 13000 | E430: 2 | F430: =E430*D430 -> 0 | G430: REINGRESO
A431: PCAJKAISE21 | B431: JUJUTSU KAISEN 21 | C431: 9786076368145 | D431: 13000 | F431: =E431*D431 -> 0
A432: PCAJKAISE22 | B432: JUJUTSU KAISEN 22 | C432: 9786075780504 | D432: 13000 | F432: =E432*D432 -> 0
A433: PCAJKAISE23 | B433: JUJUTSU KAISEN 23 | C433: 9786075784632 | D433: 13000 | F433: =E433*D433 -> 0 | G433: REINGRESO
A434: PCAJKAISE24 | B434: JUJUTSU KAISEN 24 | C434: 9786075786995 | D434: 13000 | E434: 2 | F434: =E434*D434 -> 0
A435: PCAJKAISE25 | B435: JUJUTSU KAISEN 25 | C435: 9786075821351 | D435: 13000 | E435: 2 | F435: =E435*D435 -> 0 | G435: REINGRESO
A436: PCAJKAISE26 | B436: JUJUTSU KAISEN 26 | C436: 9786075823546 | D436: 12000 | F436: =E436*D436 -> 0
A437: PCAJKAISE27 | B437: JUJUTSU KAISEN 27 | C437: 9786075826783 | D437: 13000 | F437: =E437*D437 -> 0
A438: PCAJKAISE28 | B438: JUJUTSU KAISEN 28 | C438: 9786076380260 | D438: 13000 | F438: =E438*D438 -> 0
A439: PCAJKAISE29 | B439: JUJUTSU KAISEN 29 | C439: 9786076383568 | D439: 13000 | F439: =E439*D439 -> 0
A440: PCAJKAISE30 | B440: JUJUTSU KAISEN 30 | C440: 9786076383575 | D440: 13000 | F440: =E440*D440 -> 0
A441: PCAJKAISEFB | B441: JUJUTSU KAISEN FANBOOK OFICIAL | C441: 9786076361924 | D441: 13000 | F441: =E441*D441 -> 0
A442: PCAKAGUYA01 | B442: KAGUYASAMA LOVE IS WAR 01 | C442: 9786076348321 | D442: 12500 | F442: =E442*D442 -> 0
A443: PCAKAGUYA02 | B443: KAGUYASAMA LOVE IS WAR 02 | C443: 9786076349656 | D443: 12500 | F443: =E443*D443 -> 0
A444: PCAKAGUYA03 | B444: KAGUYASAMA LOVE IS WAR 03 | C444: 9786076349663 | D444: 12500 | F444: =E444*D444 -> 0
A445: PCAKAGUYA04 | B445: KAGUYASAMA LOVE IS WAR 04 | C445: 9786075682655 | D445: 12500 | F445: =E445*D445 -> 0
A446: PCAKAGUYA05 | B446: KAGUYASAMA LOVE IS WAR 05 | C446: 9786075683003 | D446: 12500 | F446: =E446*D446 -> 0
A447: PCAKAGUYA06 | B447: KAGUYASAMA LOVE IS WAR 06 | C447: 9786075683164 | D447: 12500 | F447: =E447*D447 -> 0
... A541: PCADIABOT01 | B541: LOS DIARIOS DE LA BOTICARIA 01 | C541: 9786075785677 | D541: 13500 | F541: =E541*D541 -> 0
A542: PCADIABOT02 | B542: LOS DIARIOS DE LA BOTICARIA 02 | C542: 9786075786506 | D542: 13500 | F542: =E542*D542 -> 0 | G542: REINGRESO
A543: PCADIABOT03 | B543: LOS DIARIOS DE LA BOTICARIA 03 | C543: 9786075787534 | D543: 13500 | F543: =E543*D543 -> 0 | G543: REINGRESO
A544: PCADIABOT04 | B544: LOS DIARIOS DE LA BOTICARIA 04 | C544: 9786075788791 | D544: 13500 | F544: =E544*D544 -> 0 | G544: REINGRESO
A545: PCADIABOT05 | B545: LOS DIARIOS DE LA BOTICARIA 05 | C545: 9786075820224 | D545: 13500 | F545: =E545*D545 -> 0 | G545: REINGRESO
A546: PCADIABOT06 | B546: LOS DIARIOS DE LA BOTICARIA 06 | C546: 9786075821399 | D546: 13500 | F546: =E546*D546 -> 0 | G546: REINGRESO
A547: PCADIABOT07 | B547: LOS DIARIOS DE LA BOTICARIA 07 | C547: 9786075822495 | D547: 13500 | F547: =E547*D547 -> 0 | G547: REINGRESO
A548: PCADIABOT08 | B548: LOS DIARIOS DE LA BOTICARIA 08 | C548: 9786075823669 | D548: 13500 | F548: =E548*D548 -> 0 | G548: REINGRESO
A549: PCADIABOT09 | B549: LOS DIARIOS DE LA BOTICARIA 09 | C549: 9786075823379 | D549: 13500 | F549: =E549*D549 -> 0
A550: PCADIABOT10 | B550: LOS DIARIOS DE LA BOTICARIA 10 | C550: 9786075823539 | D550: 13500 | F550: =E550*D550 -> 0
A551: PCADIABOT11 | B551: LOS DIARIOS DE LA BOTICARIA 11 | C551: 9786075825748 | D551: 13500 | F551: =E551*D551 -> 0
A552: PCADIABOT12 | B552: LOS DIARIOS DE LA BOTICARIA 12 | C552: 9786075826790 | D552: 13500 | F552: =E552*D552 -> 0
A553: PCADIABOT13 | B553: LOS DIARIOS DE LA BOTICARIA 13 | C553: 9786075829203 | D553: 13500 | F553: =E553*D553 -> 0
A554: PCADIABOT14 | B554: LOS DIARIOS DE LA BOTICARIA 14 | C554: 9786076381205 | D554: 13500 | F554: =E554*D554 -> 0
...

Sheet Penguin
A11: NOVEDADES
A12: AUTOR | B12: NOMBRE | C12: ISBN | D12: PVP | E12: CANT. | F12: SUBTOTAL
A13: Wakui, Ken | B13: ASTRO ROYALE 2 | C13: 9786316657602 | D13: 14900 | F13: =E13*D13 -> 0
A14: Mashiro | B14: MI AMOR POR YAMADA ESTA AL NV. 999 6 | C14: 9786316657633 | D14: 14900 | F14: =E14*D14 -> 0
A15: Takamatsu, Misaki | B15: SKIP Y LOAFER 8 | C15: 9786316657640 | D15: 14900 | F15: =E15*D15 -> 0
A16: Bomhat | B16: REINO DE QUARTZ 4 | C16: 9786316657619 | D16: 14900 | F16: =E16*D16 -> 0
A17: Zec /Moscareto | B17: EL NUEVO EMPLEADO 1 | C17: 9786316657664 | D17: 22900 | E17: 1 | F17: =E17*D17 -> 0
A18: Score, Lucy | B18: EL ERROR DE MI VIDA (STORY LAKE 2) | C18: 9789877805895 | D18: 44499 | F18: =E18*D18 -> 0
A19: Jorge Pinarello | B19: ÉRASE UNA VEZ EN UN VIDEOCLUB | C19: 9789505612369 | D19: 35000 | F19: =E19*D19 -> 0
A20: Magaziner, Lauren | B20: RESUELVE EL MISTERIO. DIARIO DE ELIZA 2 | C20: 9789878121567 | D20: 39599 | F20: =E20*D20 -> 0
A21: RuNyx | B21: SOMBRA, LA (DARK VERSE 5) | C21: 9789877805932 | D21: 34999 | F21: =E21*D21 -> 0
A22: Bluey | B22: BLUEY. MINI BLUEY | C22: 9789877365825 | D22: 8599 | F22: =E22*D22 -> 0
A23: Ron, Mercedes | B23: CULPA VUESTRA | C23: 9786316620071 | D23: 41699 | F23: =E23*D23 -> 0
A24: Netflix | B24: KPOP DEMON HUNTERS: THE DELUXE JUNIOR NO | C24: 9786316620910 | D24: 23999 | F24: =E24*D24 -> 0
A25: Netflix | B25: KPOP DEMON HUNTERS: MY GOLDEN JOURNAL | C25: 9786316620927 | D25: 23999 | F25: =E25*D25 -> 0
A26: Clapés, Elizabeth | B26: ASI ES COMO LO VERAS MAÑANA | C26: 9786316620965 | D26: 30799 | F26: =E26*D26 -> 0
A27: Anónimo | B27: STICKERMANÍA - MUNDIAL | C27: 9786316718846 | D27: 8999 | F27: =E27*D27 -> 0
B28: ULTRAJUEGOS - CIRCO DEL HORROR | C28: 9786316718853 | D28: 10999 | F28: =E28*D28 -> 0
A29: Nik | B29: GATURRO 31 (TIRAS) | C29: 9789500772761 | D29: 15999 | F29: =E29*D29 -> 0
A30: Nik | B30: GATURRO 32 (TIRAS) | C30: 9789500772778 | D30: 15999 | F30: =E30*D30 -> 0
A31: Nik | B31: GATURRO 33 (TIRAS) | C31: 9789500772785 | D31: 15999 | F31: =E31*D31 -> 0
A32: Nik | B32: GATURRO 34 (TIRAS) | C32: 9789500772792 | D32: 15999 | F32: =E32*D32 -> 0
A33: Nik | B33: GATURRO 35 (TIRAS) | C33: 9789500772808 | D33: 15999 | F33: =E33*D33 -> 0
A34: Nik | B34: GATURRO 36 (TIRAS) | C34: 9789500772815 | D34: 15999 | F34: =E34*D34 -> 0
A35: Nik | B35: GATURRO 37 (TIRAS) | C35: 9789500772822 | D35: 15999 | F35: =E35*D35 -> 0
A36: Nik | B36: GATURRO 38 (TIRAS) | C36: 9789500772839 | D36: 15999 | F36: =E36*D36 -> 0
A37: Nik | B37: GATURRO 39 (TIRAS) | C37: 9789500772846 | D37: 15999 | F37: =E37*D37 -> 0
B38: PLANNER DEL PRINCIPITO | C38: 9789500773805 | D38: 19999 | F38: =E38*D38 -> 0
A39: El Bruno | B39: ESCUELA DE MONSTRUOS 7 | C39: 9789500773966 | D39: 16999 | F39: =E39*D39 -> 0
A40: Quino | B40: DEJENME INVENTAR | C40: 9789500773997 | D40: 19999 | F40: =E40*D40 -> 0
A41: Quino | B41: HUMANO SE NACE | C41: 9789500774000 | D41: 19999 | F41: =E41*D41 -> 0
A42: Vallejos, Lyna/Morro, Daniel | B42: LYNIEL 2 - EL JUEGO FINAL | C42: 9789877365832 | D42: 19999 | F42: =E42*D42 -> 0
A43: Saint-Exupéry, Antoine de/Hesse, María | B43: PRINCIPITO ILUSTRADO (MARIA HESSE) | C43: 9789878002743 | D43: 44999 | F43: =E43*D43 -> 0
B44: MANGA
A45: Kaneshiro, Muneyuki; Fujimura, Akeji | B45: AS THE GODS WILL 1 | C45: 9789878987057 | D45: 14900 | F45: =E45*D45 -> 0
A46: Kaneshiro, Muneyuki; Fujimura, Akeji | B46: AS THE GODS WILL 2 | C46: 9789878987194 | D46: 14900 | F46: =E46*D46 -> 0
A47: Kaneshiro, Muneyuki; Fujimura, Akeji | B47: AS THE GODS WILL 3 | C47: 9789878987255 | D47: 14900 | F47: =E47*D47 -> 0
A48: Kaneshiro, Muneyuki/Fujimura, Akeji | B48: AS THE GODS WILL 4 | C48: 9789878987361 | D48: 14900 | F48: =E48*D48 -> 0
A49: Kaneshiro, Muneyuki; Fujimura, Akeji | B49: AS THE GODS WILL 5 | C49: 9789878987422 | D49: 14900 | F49: =E49*D49 -> 0
A50: Kaneshiro, Muneyuki/Fujimura, Akeji | B50: AS THE GODS WILL (SECUELA) 1 | C50: 9789878987668 | D50: 22900 | F50: =E50*D50 -> 0
A51: Kaneshiro, Muneyuki/Fujimura, Akeji | B51: AS THE GODS WILL (SECUELA) 2 | C51: 9789878987811 | D51: 22900 | F51: =E51*D51 -> 0
A52: Kaneshiro, Muneyuki; Fujimura, Akeji | B52: AS THE GODS WILL (SECUELA) 3 | C52: 9789878987958 | D52: 22900 | F52: =E52*D52 -> 0
A53: Kaneshiro, Muneyuki; Fujimura, Akeji | B53: AS THE GODS WILL (SECUELA) 4 | C53: 9786316657053 | D53: 22900 | F53: =E53*D53 -> 0
A54: Kaneshiro, Muneyuki; Fujimura, Akeji | B54: AS THE GODS WILL (SECUELA) 5 | C54: 9786316657152 | D54: 22900 | F54: =E54*D54 -> 0
A55: Kaneshiro, Muneyuki/Fujimura, Akeji | B55: AS THE GODS WILL (SECUELA) 6 | C55: 9786316657244 | D55: 22900 | F55: =E55*D55 -> 0
A56: Kaneshiro, Muneyuki/Fujimura, Akeji | B56: AS THE GODS WILL (SECUELA) 7 | C56: 9786316657589 | D56: 22900 | F56: =E56*D56 -> 0
... A173: Anashin | B173: UNA HISTORIA DE ALMAS GEMELAS 6 | C173: 9786316657572 | D173: 14900 | F173: =E173*D173 -> 0
B174: POKÉMON
A175: The Pokémon Company | B175: ATLAS DE ASH KETCHUM | C175: 9789878940854 | D175: 41599 | F175: =E175*D175 -> 0
A176: The Pokémon Company | B176: AVENTURA EN PALDEA | C176: 9786316620484 | D176: 14999 | F176: =E176*D176 -> 0
A177: The Pokémon Company | B177: FUECOCO TE ELIJO A TI! | C177: 9786316620293 | D177: 26499 | F177: =E177*D177 -> 0
A178: The Pokémon Company | B178: ENCICLOPEDIA POKEMON | C178: 9789878940304 | D178: 46399 | F178: =E178*D178 -> 0
A179: The Pokémon Company | B179: GUÍA POKEMON DE ALOLA | C179: 9789873820885 | D179: 37499 | F179: =E179*D179 -> 0
A180: The Pokémon Company | B180: LA BATALLA FINAL DE ASH | C180: 9786316620163 | D180: 32299 | F180: =E180*D180 -> 0
A181: The Pokémon Company | B181: PLANNER DE POKÉMON | C181: 9786316620019 | D181: 19999 | F181: =E181*D181 -> 0
A182: The Pokémon Company | B182: POKEMON: 250 ACTIVIDADES | C182: 9786316620873 | D182: 16999 | F182: =E182*D182 -> 0
A183: The Pokémon Company | B183: POKEMON: LINEAS DEL TIEMPO | C183: 9786316620668 | D183: 28899 | F183: =E183*D183 -> 0
A184: The Pokémon Company | B184: POKEMON COMICTIVITY | C184: 9789878940519 | D184: 13699 | F184: =E184*D184 -> 0
A185: The Pokémon Company | B185: POKEMON COMICTIVITY 3: ¡DIVERSION AL MAXIMO! | C185: 9786316620026 | D185: 13699 | F185: =E185*D185 -> 0
A186: The Pokémon Company | B186: POKEMON GUÍA DEFINITIVA DE LA REGIÓN GALAR | C186: 9789874924681 | D186: 25399 | F186: =E186*D186 -> 0
... A191: The Pokémon Company | B191: POKEMON - MI PLANNER | C191: 9786316620019 | D191: 19999 | F191: =E191*D191 -> 0
B192: FIVE NIGHTS AT FREDDYS
A193: Scott Cawthon | B193: FIVE NIGHTS AT FREDDY´S CUADERNO DE SUPERVIVENCIA | C193: 9788419449511 | D193: 30799 | F193: =E193*D193 -> 0
A194: SCOTT CAWTHON | B194: FIVE NIGHTS AT FREDDY'S 1 - LOS OJOS DE PLATA | C194: 9788416867691 | D194: 39999 | F194: =E194*D194 -> 0
A195: SCOTT CAWTHON | B195: FIVE NIGHTS AT FREDDY'S 3: EL CUARTO ARMARIO | C195: 9788418014130 | D195: 42899 | F195: =E195*D195 -> 0
B196: FIVE NIGHTS AT FREDDY'S NOVELA GRÁFICA 1 OJOS DE PLATA | C196: 9788419743473 | D196: 30799 | F196: =E196*D196 -> 0
A197: Cawthon, Scott; Breed-Wrisley, Kira | B197: FIVE NIGHTS AT FREDDY'S NOVELA GRÁFICA 2 OTROS ANIMATRONICOS | C197: 9788419743749 | D197: 30799 | F197: =E197*D197 -> 0
A198: Scott Cawthon | B198: FIVE NIGHTS AT FREDDY'S. ESCALOFRÍOS DE FAZBEARS 3: 1:35 | C198: 9788419743305 | D198: 42899 | F198: =E198*D198 -> 0
A199: Scott Cawthon | B199: FIVE NIGHTS AT FREDDY'S: ESCALOFRÍOS DE FAZBEAR 1. EL PARQUE DE BOLAS | C199: 9788418870576 | D199: 30799 | F199: =E199*D199 -> 0
A200: Scott cawthorn | B200: FIVE NIGHTS AT FREDDY'S. EL JUEGO DE LALY 1 | C200: 9788419743824 | D200: 39999 | F200: =E200*D200 -> 0
A201: Cawthon, Scott; | B201: FNAF PIZZAPLEX 2. SPLAT | C201: 9788419449030 | D201: 39999 | F201: =E201*D201 -> 0
A202: Cawthon, Scott | B202: FNAF PIZZAPLEX 3 - SOMNIFOBIA | C202: 9791387517007 | D202: 39999 | F202: =E202*D202 -> 0
A203: Cawthon, Scott/Breed-Wrisley, Kira | B203: FNAF 3 NOVELA GRAFICA. EL CUARTO ARMARIO | C203: 9791387517069 | D203: 30799 | F203: =E203*D203 -> 0
B204: HARRY POTTER
A205: Rowling, J. K. | B205: APRENDE A DIBUJAR CON HARRY POTTER | C205: 9788419275905 | D205: 30599 | F205: =E205*D205 -> 0
A206: Rowling, J. K. | B206: EL MUNDO MAGICO DE HARRY POTTER | C206: 9788419275448 | D206: 69999 | F206: =E206*D206 -> 0
A207: Rowling, J.K. | B207: HARRY POTTER 1 ED. LIMITADA | C207: 9788419868282 | D207: 65299 | F207: =E207*D207 -> 0
A208: Rowling, J.K. | B208: HARRY POTTER Y LA ORDEN DEL FENIX (RELAN | C208: 9789878002521 | D208: 77999 | F208: =E208*D208 -> 0
A209: Rowling, J. K. | B209: HARRY POTTER. LIBRO DE HECHIZOS | C209: 9788419868084 | D209: 53099 | F209: =E209*D209 -> 0
A210: Rowling, J. K. | B210: HARRY POTTER LA SERIE COMPLETA (7 TOMOS) | C210: 9789878000473 | D210: 199999 | F210: =E210*D210 -> 0
A211: Rowling, J. K. | B211: HARRY POTTER 1 Y LA CAMARA SECRETA (RELANZ | C211: 9789878002088 | D211: 45199 | F211: =E211*D211 -> 0
A212: Rowling, J. K. | B212: HARRY POTTER 2 Y LA PIEDRA FILOSOFAL (RELA | C212: 9789878002095 | D212: 45199 | F212: =E212*D212 -> 0
A213: J.K. ROWLING | B213: HARRY POTTER 3 Y EL PRISIONERO DE AZKABAN | C213: 9789878000121 | D213: 28799 | F213: =E213*D213 -> 0
A214: J.K. ROWLING | B214: HARRY POPTTER 4 Y EL CALIZ DE FUEGO | C214: 9789878000138 | D214: 55599 | F214: =E214*D214 -> 0
A215: J.K. ROWLING | B215: HARRY POTTER 5 Y LA ORDEN DEL FENIX | C215: 9789878000145 | D215: 55999 | F215: =E215*D215 -> 0
A216: J.K. ROWLING | B216: HARRY POTTER 6 Y EL MISTERIO DEL PRINCIPE | C216: 9789878000152 | D216: 39999 | F216: =E216*D216 -> 0
... A221: Lewis, Kate; Davies, Paul | B221: HOGWARTS LEGACY | C221: 9789500769204 | D221: 37199 | F221: =E221*D221 -> 0
B222: STEPHEN KING
A223: King, Stephen; King, Owen | B223: BELLAS DURMIENTES | C223: 9789877257489 | D223: 38599 | F223: =E223*D223 -> 0
A224: STEPHEN KING | B224: CARRIE | C224: 9789877255058 | D224: 29999 | F224: =E224*D224 -> 0
A225: STEPHEN KING | B225: CARRIE (50 ANIVERSARIO) | C225: 9789506447397 | D225: 44599 | F225: =E225*D225 -> 0
A226: King, Stephen; Straub, Peter | B226: CASA NEGRA | C226: 9789877256314 | D226: 37399 | F226: =E226*D226 -> 0
A227: STEPHEN KING | B227: CUENTO DE HADAS | C227: 9789877256857 | D227: 37399 | F227: =E227*D227 -> 0
A228: STEPHEN KING | B228: EL MISTERIO DE SALEM'S LOT | C228: 9789877254129 | D228: 47999 | F228: =E228*D228 -> 0
A229: STEPHEN KING | B229: EL PISTOLERO - LA TORRE OSCURA INTEGRAL 2 (CÓMIC) | C229: 9788466336956 | D229: 71199 | F229: =E229*D229 -> 0
A230: King, Stephen; Straub, Peter | B230: EL TALISMAN | C230: 9789877256307 | D230: 44399 | F230: =E230*D230 -> 0
A231: STEPHEN KING | B231: EL VISITANTE | C231: 9789877255089 | D231: 32399 | F231: =E231*D231 -> 0
A232: King, Stephen | B232: HOLLY | C232: 9789877257694 | D232: 37399 | F232: =E232*D232 -> 0
A233: STEPHEN KING | B233: HOLLY | C233: 9789506446949 | D233: 54999 | F233: =E233*D233 -> 0
A234: STEPHEN KING | B234: LA MITAD OSCURA | C234: 9789877255706 | D234: 32399 | F234: =E234*D234 -> 0
...

Sheet Planeta
A10: NOVEDADES DICIEMBRE
A11: TITULO | B11: EAN | C11: PVP | D11: Cantidad | E11: Subtotal
A12: STAR WARS ANTOLOGIA (ED. LIMIT ADA) | B12: 9788491460688 | C12: 79900 | E12: =D12*C12 -> 0 | F12: NOVEDAD
A13: STAR WARS NUEVA ENCICLOPEDIA D E PERSONAJES ACTUALIZADA | B13: 9788413429427 | C13: 42900 | E13: =D13*C13 -> 0 | F13: NOVEDAD
A14: STAR WARS VESTUARIO | B14: 9788416476596 | C14: 49900 | E14: =D14*C14 -> 0 | F14: NOVEDAD
A15: STAR WARS. THE MANDALORIAN (COMIC) | B15: 9788411121934 | C15: 24900 | E15: =D15*C15 -> 0 | F15: NOVEDAD
A16: PALESTINA | B16: 9788411618458 | C16: 26900 | E16: =D16*C16 -> 0 | F16: NOVEDAD
A17: COMO SE HIZO EPISODIO VI EL RE TORNO DEL JEDI | B17: 9788491461647 | C17: 59900 | E17: =D17*C17 -> 0 | F17: NOVEDAD
A18: COMO SE HIZO STAR WARS UNA NUE VA ESPERANZA | B18: 9788416090648 | C18: 59900 | E18: =D18*C18 -> 0 | F18: NOVEDAD
A19: STAR WARS LOS PLANOS (SW BLUEP RINTS) | B19: 9788416693900 | C19: 99900 | E19: =D19*C19 -> 0 | F19: NOVEDAD
A20: EL ARTE DE STAR WARS: THE MAND ALORIAN | B20: 9788413419176 | C20: 49900 | E20: =D20*C20 -> 0 | F20: NOVEDAD
A21: STAR WARS. AHSOKA | B21: 9791387779979 | C21: 32900 | E21: =D21*C21 -> 0 | F21: NOVEDAD
A22: STAR WARS. THE MANDALORIAN (COMIC) TEMPORADA 2 | B22: 9788411618779 | C22: 32900 | E22: =D22*C22 -> 0 | F22: NOVEDAD
A23: NAUSICAA Nº 04 | B23: 9789504996064 | C23: 32900 | E23: =D23*C23 -> 0
A24: MIENTRAS YUBOOH DUERME 6 | B24: 9789504996859 | C24: 29900 | E24: =D24*C24 -> 0
A25: COMENTARIOS AL NÁUCRATO. NOVELA GRÁFICA | B25: 9789504992974 | C25: 23900 | E25: =D25*C25 -> 0
A26: ¡ABRAZA A TU AMIGO FIEL! TOY STORY | B26: 9789504996293 | C26: 29900 | E26: =D26*C26 -> 0
A27: ALAS DE SANGRE. EDICIÓN ESPECIAL LIMITADA | B27: 9786073939300 | C27: 41900 | E27: =D27*C27 -> 0
A28: PURO FÚTBOL | B28: 9789878224008 | C28: 19900 | E28: =D28*C28 -> 0
A29: CÓMO ENTRENAR A TU DRAGÓN. ESCUELA DE DRAGONES | B29: 9789504996873 | C29: 29900 | E29: =D29*C29 -> 0
A30: QUIERO VERTE OTRA VEZ | B30: 9789878223995 | C30: 19900 | E30: =D30*C30 -> 0
A31: EL MANUAL DEL HINCHA | B31: 9789878224015 | C31: 19900 | E31: =D31*C31 -> 0
A32: EL MUNDO HA VIVIDO EQUIVOCADO | B32: 9789878224022 | C32: 19900 | E32: =D32*C32 -> 0
A33: REBELIÓN EN LA GRANJA | B33: 9789878224039 | C33: 22900 | E33: =D33*C33 -> 0
A34: TWISTED 3. TWISTED HATE | B34: 9789878224084 | C34: 35900 | E34: =D34*C34 -> 0
... A40: TRIFONÍA & BALDOMERO | B40: 9789504996866 | C40: 36900 | E40: =D40*C40 -> 0
A41: OFERTA PLANETA ESPAÑA
A42: EL REY FANTASMA | B42: 9788448037963 | C42: 25900 | E42: =D42*C42 -> 0
A43: EL REY ORCO | B43: 9788448037949 | C43: 25900 | E43: =D43*C43 -> 0
A44: USAGI YOJIMBO SAGA LIBRO 4 | B44: 9788491735700 | C44: 30500 | E44: =D44*C44 -> 0
A45: USAGI YOJIMBO SAGA LIBRO 1 | B45: 9788416816446 | C45: 30500 | E45: =D45*C45 -> 0
A46: VINLAND SAGA 23 | B46: 9788413416311 | C46: 9700 | E46: =D46*C46 -> 0
A47: TEZUCOMI 1 | B47: 9788413415895 | C47: 20900 | E47: =D47*C47 -> 0
A48: TEZUCOMI 2 | B48: 9788413416854 | C48: 20900 | E48: =D48*C48 -> 0
A49: HAY ALGO MATANDO A LOS NIÑOS 1 (TAPA DURA) | B49: 9788413416441 | C49: 10900 | E49: =D49*C49 -> 0
A50: EL LOBO SOLITARIO Y SU CACHORRO 02 | B50: 9788416693184 | C50: 22000 | E50: =D50*C50 -> 0
A51: EL LOBO SOLITARIO Y SU CACHORRO 03 | B51: 9788416693191 | C51: 22000 | E51: =D51*C51 -> 0
A52: EL LOBO SOLITARIO Y SU CACHORRO 04 | B52: 9788416636594 | C52: 22000 | E52: =D52*C52 -> 0
A53: EL LOBO SOLITARIO Y SU CACHORRO 05 | B53: 9788416636600 | C53: 22000 | E53: =D53*C53 -> 0
... A73: BABYTEETH 1: EL NACIMIENTO | B73: 9788491737353 | C73: 10900 | E73: =D73*C73 -> 0
E74: =D74*C74 -> 0
A75: COMIC/MANGA
A76: TITULO | B76: EAN | C76: PVP | D76: Cantidad | E76: Subtotal
A77: 1984 (NOVELA GRÁFICA) | B77: 9789504987246 | C77: 33900 | E77: =D77*C77 -> 0
A78: ¡ABRAZA A GROOT! | B78: 9789504983408 | C78: 22900 | E78: =D78*C78 -> 0
A79: ¡ABRAZA A STITCH! | B79: 9789504975113 | C79: 16900 | E79: =D79*C79 -> 0
A80: ¿ESCUCHAS GIRL IN RED? 01 | B80: 9789504983156 | C80: 19900 | E80: =D80*C80 -> 0
A81: ¿DÓNDE ESTÁ SPIDEY? | B81: 9789504981732 | C81: 22900 | E81: =D81*C81 -> 0
A82: ¿DÓNDE ESTÁ STITCH? | B82: 9789504990703 | C82: 22900 | E82: =D82*C82 -> 0
A83: ¿DÓNDE ESTÁN LOS AVENGERS? | B83: 9789504985754 | C83: 22900 | E83: =D83*C83 -> 0
A84: ADOLF TANKOBON 01 | B84: 9789504982272 | C84: 14900 | E84: =D84*C84 -> 0
A85: ADOLF TANKOBON 02 | B85: 9789504982821 | C85: 14900 | E85: =D85*C85 -> 0
A86: ADOLF TANKOBON 03 | B86: 9789504982838 | C86: 14900 | E86: =D86*C86 -> 0
A87: ADOLF TANKOBON 04 | B87: 9789504982845 | C87: 14900 | E87: =D87*C87 -> 0
A88: ADOLF TANKOBON 05 | B88: 9789504982852 | C88: 14900 | E88: =D88*C88 -> 0
... A134: EL DULCE HOGAR DE CHI 11 | B134: 9789504989370 | C134: 13900 | E134: =D134*C134 -> 0
A135: EL DULCE HOGAR DE CHI 12 | B135: 9789504989806 | C135: 13900 | E135: =Planeta!$C135*Planeta!$D135 -> 0
A136: EL ALMANAQUE DE MI PADRE (TRAZADO) | B136: 9789504982128 | C136: 19900 | E136: =D136*C136 -> 0
A137: EL ALQUIMISTA (NOVELA GRÁFICA) | B137: 9789504987833 | C137: 38900 | E137: =D137*C137 -> 0
A138: EL ETERNAUTA (ED. ECONÓMICA) | B138: 9789504982814 | C138: 42900 | E138: =D138*C138 -> 0
A139: EL ETERNAUTA (CARTONÉ) | B139: 9789504977117 | C139: 79900 | E139: =D139*C139 -> 0
A140: EL HORROR DE DUNWICH 01 | B140: 9789504995715 | C140: 21900 | E140: =D140*C140 -> 0
A141: EL HORROR DE DUNWICH 02 | B141: 9789504996651 | C141: 19900 | E141: =D141*C141 -> 0
A142: EL LIBRO DE BILL | B142: 9789878223896 | C142: 29900 | E142: =D142*C142 -> 0
A143: EL LIBRO DE BILL - TAPA DURA | B143: 9789564086521 | C143: 49900 | E143: =D143*C143 -> 0
A144: EL MORADOR DE LAS TINIEBLAS (MANGA) | B144: 9789504992806 | C144: 22900 | E144: =D144*C144 -> 0
A145: EL RULAS 1. EL RULAS Y LA MOTILLO PERDIDA | B145: 9789507326370 | C145: 43900 | E145: =D145*C145 -> 0
A146: EN LA NOCHE DE LOS TIEMPOS | B146: 9789504993964 | C146: 37900 | E146: =D146*C146 -> 0
A147: FROM HELL | B147: 9789504976493 | C147: 55900 | E147: =D147*C147 -> 0
... A208: LA LLAMADA DE CTHULHU (MANGA) | B208: 9789504987239 | C208: 22900 | E208: =D208*C208 -> 0
A209: LECTOR OMNISCIENTE Nº 01 | B209: 9789504995838 | C209: 29900 | D209: 1 | E209: =D209*C209 -> 0
A210: LECTOR OMNISCIENTE Nº 02 | B210: 9789504995838 | C210: 29900 | E210: =D210*C210 -> 0
A211: LILO & STITCH. EL CÓMIC | B211: 9789504992929 | C211: 22900 | E211: =D211*C211 -> 0
A212: LOLA VENDETTA. KATANAZO AL AMOR ROMÁNTICO | B212: 9789504985037 | C212: 31900 | E212: =D212*C212 -> 0
A213: LOS CUATRO FANTÁSTICOS PARA COLOREAR | B213: 9789504992905 | C213: 17900 | E213: =D213*C213 -> 0
A214: LOS VENGADORES DEL FUTURO (MANGA) | B214: 9789504983910 | C214: 20900 | E214: =D214*C214 -> 0
A215: MIENTRAS YUBOOH DUERME 01 | B215: 9789504982722 | C215: 19900 | E215: =D215*C215 -> 0
A216: MIENTRAS YUBOOH DUERME 02 | B216: 9789504982739 | C216: 19900 | E216: =D216*C216 -> 0
A217: MIENTRAS YUBOOH DUERME 03 | B217: 9789504982746 | C217: 19900 | E217: =D217*C217 -> 0
A218: MIENTRAS YUBOOH DUERME 04 | B218: 9789504987703 | C218: 19900 | E218: =D218*C218 -> 0
A219: MIENTRAS YUBOOH DUERME 05 | B219: 9789504989868 | C219: 19900 | E219: =D219*C219 -> 0
A220: MITOS NÓRDICOS 1 (CÓMIC) | B220: 9789504981466 | C220: 25900 | E220: =D220*C220 -> 0
A221: MITOS NÓRDICOS 2 (CÓMIC) | B221: 9789504989356 | C221: 25900 | E221: =D221*C221 -> 0
... A296: TOKYO GIRLS 3 | B296: 9789504988649 | C296: 14900 | E296: =D296*C296 -> 0
A297: TOKYO GIRLS 4 | B297: 9789504989790 | C297: 14900 | E297: =Planeta!$C297*Planeta!$D297 -> 0
A298: TOKYO GIRLS 5 | B298: 9789504990772 | C298: 14900 | E298: =D298*C298 -> 0
A299: TOKYO GIRLS 6 | B299: 9789504992776 | C299: 14900 | E299: =D299*C299 -> 0
A300: TOKYO GIRLS 7 | B300: 9789504996057 | C300: 14900 | E300: =D300*C300 -> 0
A301: TRANSFORMERS. MORE THAN MEETS THE EYE 4 | B301: 9788416816200 | C301: 43900 | E301: =D301*C301 -> 0
A302: TRANSFORMERS. ROBOTS IN DISGUISE 1 | B302: 9788416244072 | C302: 22900 | E302: =D302*C302 -> 0
A303: TRANSFORMERS: CYBERTRON OSCURO | B303: 9788416693153 | C303: 31900 | E303: =D303*C303 -> 0
A304: TRANSFORMERS: MARVEL UK 1 | B304: 9788415921189 | C304: 31900 | E304: =D304*C304 -> 0
A305: TWISTED WONDERLAND 01 | B305: 9789504986522 | C305: 19900 | E305: =D305*C305 -> 0
A306: TWISTED WONDERLAND 02 | B306: 9789504987307 | C306: 19900 | E306: =D306*C306 -> 0
A307: TWISTED WONDERLAND 03 | B307: 9789504988502 | C307: 19900 | E307: =D307*C307 -> 0
A308: TWISTED WONDERLAND 04 | B308: 9789504989295 | C308: 19900 | E308: =D308*C308 -> 0
A309: USAGI YOJIMBO FANTAGRAPHICS INTEGRAL 1 | B309: 9789504985006 | C309: 38900 | E309: =D309*C309 -> 0
A310: LIBROS
A311: ¿SUEÑAN LOS ANDROIDES CON OVEJAS ELÉCTRICAS? (BLADE RUNNER) | B311: 9789505472109 | C311: 48900 | E311: =D311*C311 -> 0
A312: ¿Y A TI QUÉ TE PICA? | B312: 9789504985334 | C312: 49900 | E312: =D312*C312 -> 0
...

Sheet Deux-PopFiction
A12: LANZAMIENTOS
A14: PRODUCTO | B14: SELLO | C14: TITULO | D14: ISBN | E14: pvp ACTUAL | F14: Cantidad | G14: Subtotal
A15: MANGA | B15: POP FICTION | C15: LOVE IN HELL 2 | D15: 9789878905150 | E15: 19500 | G15: =F15*E15 -> 0 | H15: NOVEDAD
A16: Historieta Argentina | B16: Deux | C16: BLOODTOWN | D16: 9789871485345 | E16: 23900 | G16: =F16*E16 -> 0
A17: Historieta Argentina | B17: Deux | C17: LOS SIGLOS OSCUROS VOL 3 | D17: 9786316536907 | E17: 25900 | G17: =F17*E17 -> 0
A18: Historieta Argentina | B18: Deux | C18: FALKA 2: EL CRISTAL ROJO | D18: 9789871485352 | E18: 24400 | G18: =F18*E18 -> 0
A19: Historieta Argentina | B19: Deux | C19: ¡NO MATARÁS! | D19: 9789872347093 | E19: 22900 | G19: =F19*E19 -> 0
A20: Historieta Argentina | B20: Deux | C20: EL COLOR DE LA MUERTE | D20: 9789871485468 | E20: 23900 | G20: =F20*E20 -> 0
A21: PRODUCTO | B21: SELLO | C21: DEUX ESTUDIO | E21: pvp ACTUAL | F21: Cantidad | G21: Subtotal
A22: Historieta Argentina | B22: Deux | C22: ¿POR QUÉ DESAPARECIERON LOS CABALLEROS? | D22: 9786316536815 | E22: 17900 | G22: =F22*E22 -> 0
A23: Cómic Americano | B23: Deux | C23: 30 DIAS DE NOCHE LA SAGA ORIGINAL | D23: 7798290036054 | E23: 10000 | G23: =F23*E23 -> 0
A24: Cómic Americano | B24: Pop Fiction | C24: ALIEN LA HISTORIA ILUSTRADA | D24: 9789874717153 | E24: 28500 | G24: =F24*E24 -> 0
A25: Comic nacional | B25: Deux | C25: ALFABETO EROTICO (EL TOMI / CLARA RODRIGUEZ) | D25: 9786319046939 | E25: 18900 | G25: =F25*E25 -> 0
A26: COMIC NACIONAL | B26: DEUX | C26: ALMANZOR | D26: 9786319046946 | E26: 19900 | G26: =F26*E26 -> 0
A27: Historieta Argentina | B27: Deux | C27: ARGENTINA POTENCIA | D27: 9789871485802 | E27: 24900 | G27: =F27*E27 -> 0
A28: Cómic Americano | B28: Deux | C28: BAD BOY (FRANK MILLER-SIMON BISLEY) | D28: 9789871485307 | E28: 21900 | G28: =F28*E28 -> 0
A29: Historieta Argentina | B29: Deux | C29: BIG RAG | D29: 9786316536372 | E29: 29500 | G29: =F29*E29 -> 0
A30: Historieta Argentina | B30: Deux | C30: BROWNING & COPPER | D30: 9786316536570 | E30: 24900 | G30: =F30*E30 -> 0
A31: Historieta Argentina | B31: Deux | C31: CABALLEROS COLECCIÓN ESENCIAL TOMO 1 | D31: 9789871485093 | E31: 24900 | G31: =F31*E31 -> 0
A32: COMIC NACIONAL | B32: DEUX | C32: CABALLEROS COLECCIÓN ESENCIAL TOMO 3 | D32: 9786316536433 | E32: 24900 | G32: =F32*E32 -> 0
A33: Historieta Argentina | B33: Deux | C33: CABALLEROS COLECCIÓN ESENCIAL TOMO 4 | D33: 9786316536594 | E33: 24900 | G33: =F33*E33 -> 0
... A53: Historieta Argentina | B53: Deux | C53: CRONICAS DE LOCKANN | D53: 9789871485901 | E53: 22900 | G53: =F53*E53 -> 0
A54: Historieta Argentina | B54: Deux | C54: CRONICAS DEL TIEMPO MEDIO INTEGRAL BYN | D54: 9789874881366 | E54: 29900 | G54: =F54*E54 -> 0
A55: Historieta Argentina | B55: Deux | C55: CRONICAS DEL TIEMPO MEDIO INTEGRAL COLOR | D55: 9789871485857 | E55: 35900 | G55: =F55*E55 -> 0
A56: Historieta Argentina | B56: Deux | C56: CRONICAS DEL TIEMPO MEDIO: LA PRECUELA VOL 1 | D56: 9789871485994 | E56: 23500 | G56: =F56*E56 -> 0
A57: Historieta Argentina | B57: Deux | C57: CRONICAS DEL TIEMPO MEDIO: LA PRECUELA VOL 2 | D57: 9786316536099 | E57: 23500 | G57: =F57*E57 -> 0
A58: Historieta Argentina | B58: Deux | C58: CRONICAS DEL TIEMPO MEDIO: LA PRECUELA VOL 3 (FINAL) | D58: ISBN A CONFIRMAR | E58: 23500 | G58: =F58*E58 -> 0
A59: Historieta Argentina | B59: Deux | C59: CUENTOS PARA NADA INFANTILES | D59: 9786316536143 | E59: 22900 | G59: =F59*E59 -> 0
A60: Historieta Argentina | B60: Deux | C60: DEREK OBRA COMPLETA | D60: ISBN A CONFIRMAR | E60: 29900 | G60: =F60*E60 -> 0
A61: Historieta Argentina | B61: Deux | C61: DON NICOLA | D61: 9786316536266 | E61: 29900 | G61: =F61*E61 -> 0
A62: Historieta Argentina | B62: Deux | C62: EKATON EL PUEBLO PERDIDO DEL ESPACIO 2da Ed. | D62: 9786316536105 | E62: 23900 | G62: =F62*E62 -> 0
A63: Historieta Argentina | B63: Deux | C63: EL BUITRE ES UN AVE DE PASO | D63: ISBN A CONFIRMAR | E63: 27500 | G63: =F63*E63 -> 0
A64: Historieta Argentina | B64: Deux | C64: EL COBRA VOLUMEN 1 (REEDICIÓN) | D64: 9789874881380 | E64: 21900 | G64: =F64*E64 -> 0
A65: Historieta Argentina | B65: Deux | C65: EL COBRA VOLUMEN 2 | D65: 9786316536242 | E65: 21900 | G65: =F65*E65 -> 0
A66: COMIC NACIONAL | B66: DEUX | C66: EL COBRA VOLUMEN 3 | D66: 9786316536440 | E66: 23900 | G66: =F66*E66 -> 0
A67: COMIC NACIONAL | B67: DEUX | C67: EL COBRA 4 | D67: 9786316536532 | E67: 23900 | G67: =F67*E67 -> 0
A68: Comic nacional | B68: Deux | C68: EL CONVENTILLO DE DON NICOLA | D68: 9786316536266 | E68: 29900 | G68: =F68*E68 -> 0
A69: Historieta Argentina | B69: Deux | C69: EL CONVENTILLO DE DON NICOLA 2 | D69: 9786316536587 | E69: 29900 | G69: =F69*E69 -> 0
A70: COMIC EUROPEO | B70: DEUX | C70: EL CORAZÓN CORONADO | D70: 9789871485321 | E70: 29500 | G70: =F70*E70 -> 0
A71: Historieta Argentina | B71: Deux | C71: EL ESPIRITU DE MASCARIN (TOMO UNICO) | D71: 9786316536211 | E71: 29900 | G71: =F71*E71 -> 0
A72: Historieta Argentina | B72: Deux | C72: EL EXTRANJERO 2da Edición | D72: 9789871485987 | E72: 21900 | G72: =F72*E72 -> 0
A73: Historieta Argentina | B73: Deux | C73: EL EXTRAÑO JUICIO A ROY ELY | D73: 9789871485918 | E73: 21900 | G73: =F73*E73 -> 0
A74: Historieta Argentina | B74: Deux | C74: EL LIBRO DE LAS ALMAS PERDIDAS Y EL FARO DE LAS CONDENADAS | D74: 9786316536525 | E74: 22900 | G74: =F74*E74 -> 0
A75: Historieta Argentina | B75: Deux | C75: EL IMPERIO Y LOS HARAPOS | D75: 9786316536112 | E75: 22900 | G75: =F75*E75 -> 0
A76: Historieta Argentina | B76: Deux | C76: EL ÚLTIMO DE LOS MOHICANOS | D76: 9786316536600 | E76: 19900 | G76: =F76*E76 -> 0
A77: Historieta Argentina | B77: Deux | C77: EL RIO OCULTO | D77: 9786316536174 | E77: 19900 | G77: =F77*E77 -> 0
A78: manga mahnwa | B78: Deux | C78: EL VUELO | D78: 9789871485062 | E78: 17900 | G78: =F78*E78 -> 0
B79: TG | C79: EPIKOS/ETERNITY SCHOOL | D79: 9786319046915 | E79: 21900 | G79: =F79*E79 -> 0
A80: Historieta Argentina | B80: Deux | C80: FANTASIAS | D80: 9789871485888 | E80: 19900 | G80: =F80*E80 -> 0
A81: Historieta Argentina | B81: Deux | C81: GENERACIÓN MALDITA | D81: 9786316536785 | E81: 29500 | G81: =F81*E81 -> 0
A82: Historieta Argentina | B82: DEUX | C82: GOETH | D82: 9786316536860 | E82: 22500 | G82: =F82*E82 -> 0
A83: Historieta Argentina | B83: Deux | C83: HACIA MUNDOS EXTRAÑOS | D83: 9786316536167 | E83: 19900 | G83: =F83*E83 -> 0
A84: Historieta Argentina | B84: Deux | C84: HENGA & HOR VOLUMEN 1 | D84: 9786316536549 | E84: 29900 | G84: =F84*E84 -> 0
A85: Historieta Argentina | B85: Deux | C85: HENGA & HOR VOLUMEN 2 | D85: 9786316536617 | E85: 29900 | G85: =F85*E85 -> 0
A86: COMIC NACIONAL | B86: DEUX | C86: HERCULES MYST | D86: 9786316536488 | E86: 24900 | G86: =F86*E86 -> 0
A87: Historieta Argentina | B87: Deux | C87: HERNAN EL CORSARIO | D87: 9789871485123 | E87: 21900 | G87: =F87*E87 -> 0
A88: Historieta Argentina | B88: Deux | C88: HIPERNOVA | D88: 9789871485925 | E88: 21900 | G88: =F88*E88 -> 0
A89: Historieta Argentina | B89: Deux | C89: HORACIO LALIA, UNA VIDA DIBUJADA | D89: 9789878896830 | E89: 24900 | G89: =F89*E89 -> 0
A90: Historieta Argentina | B90: Deux | C90: HORIZONTES PERDIDOS VOL 3 | D90: 9786316536129 | E90: 21900 | G90: =F90*E90 -> 0
A91: Historieta Argentina | B91: Deux | C91: HORIZONTES PERDIDOS VOLUMEN 4 | D91: 9786316536235 | E91: 21900 | G91: =F91*E91 -> 0
A92: COMIC NACIONAL | B92: DEUX | C92: HORIZONTES PERDIDOS 5: LA GUERRERA DE LAS ESTRELLAS | D92: 9786316536495 | E92: 21900 | G92: =F92*E92 -> 0
A93: COMIC EUROPEO | B93: DEUX | C93: INFIDEL | D93: 9789878905167 | E93: 29500 | G93: =F93*E93 -> 0
A94: COMIC NACIONAL | B94: DEUX | C94: INVASIÓN 55 | D94: 9786316536464 | E94: 17900 | G94: =F94*E94 -> 0
A95: COMIC NACIONAL | B95: DEUX | C95: KRANTZ: FÁBULA | D95: 9786316536389 | E95: 22900 | G95: =F95*E95 -> 0
A96: Historieta Argentina | B96: Deux | C96: KRANTZ VOLUMEN 1 REEDICION AMPLIADA | D96: 9789871485390 | E96: 23900 | G96: =F96*E96 -> 0
A97: Historieta Argentina | B97: Deux | C97: KRANTZ VOLUMEN 2 REEDICION | D97: 9789871485833 | E97: 22900 | G97: =F97*E97 -> 0
A98: Historieta Argentina | B98: Deux | C98: KRANTZ VOLUMEN 3 (FINAL DE SERIE) | D98: 9786316536389 | E98: 22900 | G98: =F98*E98 -> 0
A99: Historieta Argentina | B99: DEUX | C99: KINTSUGHI: CICATRICES DORADAS | D99: 9786316536884 | E99: 22900 | G99: =F99*E99 -> 0
A100: Historieta Argentina | B100: Deux | C100: LA MAGA | D100: 9789874881328 | E100: 20900 | G100: =F100*E100 -> 0
A101: COMIC EUROPEO | B101: DEUX | C101: LA METAMORFOSIS | D101: 9786316536327 | E101: 23900 | G101: =F101*E101 -> 0
A102: Historieta Argentina | B102: Deux | C102: LA SOLDADERA (BRECCIA) | D102: 9786316536136 | E102: 25900 | G102: =F102*E102 -> 0
A103: MANGA | B103: POP FICTION | C103: LOVE IN HELL 1 | D103: 9789874747877 | E103: 17900 | G103: =F103*E103 -> 0
A104: MANGA | B104: POP FICTION | C104: LIFE X01 VOL 1 | D104: 9789878905174 | E104: 19500 | G104: =F104*E104 -> 0
A105: MANGA | B105: POP FICTION | C105: LIFE X01 VOL 2 | D105: 9789874747822 | E105: 19500 | G105: =F105*E105 -> 0
A106: Historieta Argentina | B106: Deux | C106: LIMITE EXTERIOR | D106: 9786316536150 | E106: 24900 | G106: =F106*E106 -> 0
A107: COMIC NACIONAL | B107: DEUX | C107: LOS AÑOS METÁLICOS | D107: 9789871485819 | E107: 22900 | G107: =F107*E107 -> 0
A108: COMIC NACIONAL | B108: DEUX | C108: LOS ENIGMAS DEL PAMI | D108: 9786316536280 | E108: 29900 | G108: =F108*E108 -> 0
A109: Comic nacional | B109: Deux | C109: LOS SIGLOS OSCUROS 1 | D109: 9786316536648 | E109: 23900 | G109: =F109*E109 -> 0
A110: Historieta Argentina | B110: Deux | C110: LOS SIGLOS OSCUROS VOL 2 | D110: 9786316536747 | E110: 28900 | G110: =F110*E110 -> 0
A111: Historieta Argentina | B111: Deux | C111: LORD JIM | D111: 9786316536556 | E111: 24900 | G111: =F111*E111 -> 0
A112: Historieta Argentina | B112: Deux | C112: MANDY RILEY VOLUMEN 1 | D112: 9789874881342 | E112: 22900 | G112: =F112*E112 -> 0
A113: Historieta Argentina | B113: Deux | C113: MANDY RILEY VOLUMEN 2 | D113: 9786316536051 | E113: 22900 | G113: =F113*E113 -> 0
A114: Historieta Argentina | B114: Deux | C114: MANDY RILEY VOLUMEN 3 | D114: 9786316536198 | E114: 22900 | G114: =F114*E114 -> 0
A115: Comic nacional | B115: Deux | C115: MANO BLANCA | D115: 9786316536662 | E115: 24900 | G115: =F115*E115 -> 0
A116: Historieta Argentina | B116: DEUX | C116: MANO NEGRA Y OTROS RELATOS | D116: 9786316536877 | E116: 23900 | G116: =F116*E116 -> 0
A117: Comic nacional | B117: deux | C117: MACHINARIUM | D117: 9786316536334 | E117: 21900 | G117: =F117*E117 -> 0
A118: COMIC NACIONAL | B118: DEUX | C118: MACK & TIERRA DE MONSTRUOS | D118: 9786316536426 | E118: 21900 | G118: =F118*E118 -> 0
A119: Historieta Argentina | B119: Deux | C119: MATAR AL TIRANO | D119: 9786316536259 | E119: 23900 | G119: =F119*E119 -> 0
A120: COMIC NACIONAL | B120: DEUX | C120: METRO CARGUERO | D120: 9786316536419 | E120: 18900 | G120: =F120*E120 -> 0
A121: Historieta Argentina | B121: Deux | C121: MUJERES EN GUERRA | D121: 9789874881335 | E121: 24900 | G121: =F121*E121 -> 0
A122: Historieta Argentina | B122: Deux | C122: NAIM DE LOS TOO | D122: 9789874881304 | E122: 22900 | G122: =F122*E122 -> 0
A123: Historieta Argentina | B123: Deux | C123: NEKRODAMUS VOLUMEN 1 | D123: 9786316536082 | E123: 23900 | G123: =F123*E123 -> 0
A124: Historieta Argentina | B124: Deux | C124: NEKRODAMUS VOLUMEN 2 (REIMPRESION) | D124: 9789874881397 | E124: 23900 | G124: =F124*E124 -> 0
A125: Historieta Argentina | B125: Deux | C125: NEKRODAMUS VOLUMEN 3 | D125: 9786316536082 | E125: 23900 | G125: =F125*E125 -> 0
A126: Historieta Argentina | B126: Deux | C126: NEKRODAMUS VOLUMEN 4 | D126: 9786316536204 | E126: 23900 | G126: =F126*E126 -> 0
A127: Historieta Argentina | B127: Deux | C127: NEKRODAMUS 5 | D127: 9786316536365 | E127: 23900 | G127: =F127*E127 -> 0
A128: Historieta Argentina | B128: Deux | C128: OTRAS HISTORIAS DE VAMPIROS (REEDICIÓN) | D128: 9789871485932 | E128: 21900 | G128: =F128*E128 -> 0
... A141: Historieta Argentina | B141: Deux | C141: REPÓQUER DE DAMAS | D141: 9786316536686 | E141: 23900 | G141: =F141*E141 -> 0
A142: COMIC EUROPEO | B142: Deux | C142: REY ROSA | D142: 9789871485789 | E142: 19500 | G142: =F142*E142 -> 0
A143: Historieta Argentina | B143: Deux | C143: SIMON (TRILLO / RISSO) | D143: 7798290035958 | E143: 9900 | G143: =F143*E143 -> 0
...

Sheet Hotel de las Ideas
A10: Autor | B10: Título | C10: ISBN | D10: PVP | E10: Cantidad | F10: Subtotal
A11: varios | B11: EN LA ESQUINA DE MI BARRIO | C11: 9786319145649 | D11: 18000 | F11: =E11*D11 -> 0 | G11: NOVEDAD
A12: KAGO, SHINTARO | B12: DEMENCIA 21 | C12: 9789874164933 | D12: 26000 | F12: =E12*D12 -> 0
A13: KAGO, SHINTARO | B13: DEMENCIA 21 Vol. 2 | C13: 9786319145601 | D13: 26000 | F13: =E13*D13 -> 0
A14: SALA,GUSTAVO | B14: ¡VIVA LA CACA! | C14: 9789874164032 | D14: 17000 | F14: =E14*D14 -> 0
A15: BRECCIA, ALBERTO | B15: ¿DRÁCULA, DRACÚL, VLAD?¡BAH…! | C15: 9789874164216 | D15: 19000 | F15: =E15*D15 -> 0
A16: AGRIMBAU, DIEGO | B16: ¿QUIÉN MATÓ A REXTON? | C16: 9789874164162 | D16: 20000 | F16: =E16*D16 -> 0
A17: CALVI, FERNANDO | B17: AL REY DE CONSTANTINOPLA | C17: 9789874164247 | D17: 17000 | F17: =E17*D17 -> 0
A18: MANCINI, PEDRO | B18: ALIEN TRISTE | C18: 9789874592200 | D18: 20000 | F18: =E18*D18 -> 0
A19: MANCINI, PEDRO | B19: ALIEN TRISTE. DÍAS ESPECTRALES | C19: 9789874164605 | D19: 20000 | F19: =E19*D19 -> 0
A20: FEMIMUTANCIA | B20: ALIENIGENA | C20: 9789874164230 | D20: 20000 | F20: =E20*D20 -> 0
A21: CALVI, FERNANDO | B21: ALTAVISTA | C21: 9789873344879 | D21: 22000 | F21: =E21*D21 -> 0
A22: LUNIK, ALEJANDRA | B22: ANDÁ A LAVAR LOS PLATOS | C22: 9789874164346 | D22: 19000 | F22: =E22*D22 -> 0
A23: TEJADA-DEARMAS | B23: APAGÓN | C23: 9789874164629 | D23: 20000 | F23: =E23*D23 -> 0
... A121: CALVI, FERNANDO | B121: ZONIA | C121: 9789874164490 | D121: 17000 | F121: =E121*D121 -> 0
B123: AGUA NEGRA
A124: AGRIMBAU-PIETRO | B124: CIELOALTO | C124: 9789872774769 | D124: 19000 | F124: =E124*D124 -> 0
A125: BOBILLO, JUAN | B125: COCA, RAMÓN Y FERNET | C125: 9789872774745 | D125: 13000 | F125: =E125*D125 -> 0
A126: AA.VV. | B126: ENTRELINEAS | C126: 2408-3844 | D126: 13000 | F126: =E126*D126 -> 0
A127: VÁZQUEZ, LAURA | B127: FUERA DE CUADRO | C127: 9789872774776 | D127: 19000 | F127: =E127*D127 -> 0
A128: AA.VV. | B128: MAL TIEMPO | C128: 9789872774752 | D128: 13000 | F128: =E128*D128 -> 0
A129: SAENZ VALIENTE, JUAN | B129: MATUFIA | C129: 9789874501837 | D129: 13000 | F129: =E129*D129 -> 0
A130: TREIBEL-BOBILLO | B130: PLAN C | C130: 9789874501844 | D130: 19000 | F130: =E130*D130 -> 0
A131: AMAYA-HURÓN-ORTIZ | B131: ZOK! | C131: 9789874501820 | D131: 13000 | F131: =E131*D131 -> 0
B135: TOTAL HOTEL DE LAS IDEAS | F135: =SUM(F1:F134) -> 0

Sheet V&R
A1: NOVEDADES
A2: JULIE CAMEL (ILUSTRACIONES) | B2: MM - CREA TUS MUÑECAS MEXICANAS - GABRIELA | C2: 9789877478921 | D2: 25500 | F2: =E2*D2 -> 0
A3: JULIE CAMEL (ILUSTRACIONES) | B3: MM - CREA TUS MUÑECAS PORTUGUESAS - ROSA | C3: 9789877479997 | D3: 25500 | F3: =E3*D3 -> 0
A4: JULIE CAMEL (ILUSTRACIONES) | B4: MM - CREA TUS MUÑECAS TAILANDESAS - ANONG | C4: 9789877479973 | D4: 25500 | F4: =E4*D4 -> 0
A5: JULIE CAMEL (ILUSTRACIONES) | B5: MM - CREA TUS MUÑECAS ALEMANAS - CLARA | C5: 9789877479966 | D5: 25500 | F5: =E5*D5 -> 0
A6: JENNIFER NIVEN | B6: CUANDO FUIMOS MONSTRUOS | C6: 9786313006472 | D6: 42000 | F6: =E6*D6 -> 0
A7: ANIBAL LITVIN | B7: EL LIBRO DE ORO DE LA SCALONETA | C7: 9786313006595 | D7: 26000 | F7: =E7*D7 -> 0
A8: ELEANOR HAWKEN | B8: CRIATURAS MONSTRUOSAS | C8: 9786313004959 | D8: 51000 | F8: =E8*D8 -> 0
A9: MÉLANIE GRANDGIRARD | B9: BUSCA Y ENCUENTRA - MI ESCUELA | C9: 9786313004560 | D9: 32000 | F9: =E9*D9 -> 0
A10: SIMON MUGFORD | B10: ESTRELLAS DEL FÚTBOL: MBAPPÉ | C10: 9786313006113 | D10: 17000 | F10: =E10*D10 -> 0
A11: GALE - CHIAK | B11: FÚTBOL A TODO COLOR | C11: 9786313006496 | D11: 18000 | F11: =E11*D11 -> 0
A12: SHAKESPEARE, WILLIAN | B12: ROMEO Y JULIETA | C12: 9786313006816 | D12: 19800 | F12: =E12*D12 -> 0
A13: MACHIDA, SONOKO | B13: LA TIENDA JUNTO AL MAR | C13: 9786313006601 | D13: 38000 | F13: =E13*D13 -> 0
... A24: NOELIA PACE | B24: SESIÓN ABIERTA : LAS ALMAS CONECTAN, EL ESPÍRITU SANA - ED DE LUJO | C24: 9786313005444 | D24: 40000 | F24: =E24*D24 -> 0
A25: NOVEDADES ABRIL
A26: KATH JEWITT | B26: YO SOY...VALIENTE | C26: 9786313004003 | D26: 20000 | F26: =E26*D26 -> 0
A27: KATH JEWITT | B27: YO SOY... FELIZ | C27: 9786313003990 | D27: 20000 | F27: =E27*D27 -> 0
A28: KATH JEWITT | B28: YO SOY... PACIENTE | C28: 9786313003983 | D28: 20000 | F28: =E28*D28 -> 0
A29: KATH JEWITT | B29: YO SOY... AMABLE | C29: 9786313004027 | D29: 20000 | F29: =E29*D29 -> 0
A30: ANÓNIMO | B30: MANUAL DE SUPERVIVENCIA SKIBIDI TOILET - OFICIAL | C30: 9786313006267 | D30: 23000 | F30: =E30*D30 -> 0
A31: KIM BUSSING | B31: CAMBIO DE PRINCESAS - CENICIENTA Y LA BESTIA O BELLA Y EL ZAPATITO DE CRISTAL | C31: 9786313006465 | D31: 37000 | F31: =E31*D31 -> 0
A32: YOKO MURE | B32: UN DÍA PARA SOPAS, PAN Y GATOS | C32: 9786313006090 | D32: 36000 | F32: =E32*D32 -> 0
A33: BAL KHABRA | B33: REVOLVE | C33: 9786313006489 | D33: 40000 | F33: =E33*D33 -> 0
A34: AUSTIN BAECHLE | B34: LOS AVENGERS - EL LIBRO OFICIAL PARA COLOREAR FUNKO POP! | C34: 9786313005147 | D34: 23000 | F34: =E34*D34 -> 0
A35: ADRIANA ALLEGRI | B35: LA CASA DE LOS GIRASOLES | C35: 9786313006441 | D35: 41000 | F35: =E35*D35 -> 0
A36: SIMON MUGFORD | B36: ESTRELLAS DEL FÚTBOL: MESSI | C36: 9786313006106 | D36: 17000 | F36: =E36*D36 -> 0
A37: SIMON MUGFORD | B37: ESTRELLAS DEL FÚTBOL: RONALDO | C37: 9786313006120 | D37: 17000 | F37: =E37*D37 -> 0
... A39: BETA SUÁREZ | B39: ROTO | C39: 9786313006458 | D39: 37000 | F39: =E39*D39 -> 0
A40: NOVEDADES MARZO
A41: ANÓNIMO | B41: MENTES BRILLANTES: 8-9 AÑOS | C41: 9786313003563 | D41: 15000 | F41: =E41*D41 -> 0
A42: ANÓNIMO | B42: MENTES BRILLANTES: 7-8 AÑOS | C42: 9786313003556 | D42: 15000 | F42: =E42*D42 -> 0
A43: ANÓNIMO | B43: MENTES BRILLANTES: 6-7 AÑOS | C43: 9786313003549 | D43: 15000 | F43: =E43*D43 -> 0
A44: ANÓNIMO | B44: MENTES BRILLANTES: 5-6 AÑOS | C44: 9786313003532 | D44: 15000 | F44: =E44*D44 -> 0
A45: ANÓNIMO | B45: MENTES BRILLANTES: 4-5 AÑOS | C45: 9786313003525 | D45: 15000 | F45: =E45*D45 -> 0
A46: ANÓNIMO | B46: MENTES BRILLANTES: 3-4 AÑOS | C46: 9786313003518 | D46: 15000 | F46: =E46*D46 -> 0
A47: SIMON MUGFORD | B47: SUPERESTRELLAS DEL DEPORTE: VERSTAPPEN | C47: 9786313005758 | D47: 17000 | F47: =E47*D47 -> 0
A48: SIMON MUGFORD | B48: SUPERESTRELLAS DEL DEPORTE: HAMILTON | C48: 9786313005741 | D48: 17000 | F48: =E48*D48 -> 0
A49: ELEONORA MERIGHI | B49: LAS RUNAS CONTADAS | C49: 9786313006410 | D49: 30000 | F49: =E49*D49 -> 0
A50: JENNIFER HARTMANN | B50: MIENTRAS SIGA LATIENDO | C50: 9786313006342 | D50: 42900 | F50: =E50*D50 -> 0
A51: REBBECCA YARROS | B51: NOVA | C51: 9786313006359 | D51: 46200 | F51: =E51*D51 -> 0
A52: MARIANO CATTANEO | B52: NO OLVIDES QUE ESTOY MUERTA | C52: 9786313005635 | D52: 35200 | F52: =E52*D52 -> 0
A53: DANIEL BOGIAIZIAN | B53: PREOCUPARSE DE MÁS | C53: 9786313006250 | D53: 38000 | F53: =E53*D53 -> 0
A54: NOVEDADES FEBRERO
A55: JAMES NORBURY | B55: SIGUIENDO A LA LUNA | C55: 9786313004454 | D55: 50600 | F55: =E55*D55 -> 0
A56: SIERRA SIMONE | B56: PADRE: PERDÓNAME PORQUE HE PECADO - ED. DE LUJO TD | C56: 9786313004249 | D56: 55000 | F56: =E56*D56 -> 0
A57: JODI PICOULT | B57: CON CUALQUIER OTRO NOMBRE | C57: 9786313004256 | D57: 59000 | F57: =E57*D57 -> 0
A58: ANÓNIMO | B58: CAMINO AL MUNDIAL 2026 | C58: 9786313005321 | D58: 24000 | F58: =E58*D58 -> 0
A59: JEN WILLIAMS | B59: LOS INSOMNES | C59: 9786313005208 | D59: 42900 | F59: =E59*D59 -> 0
A60: ELLIOTT ROSE | B60: PERSIGUIENDO LO SALVAJE | C60: 9786313006007 | D60: 42000 | F60: =E60*D60 -> 0
A61: SKYLA ARNDT | B61: CASA DE CORAZONES | C61: 9786313006069 | D61: 40700 | F61: =E61*D61 -> 0
A62: JAY HEINRICHS | B62: GUÍA DE ARISTÓTELES PARA LA AUTOPERSUASIÓN - TRANSFORMA TU MANERA DE PENSAR, DECIDIR Y ACTUAR CON LAS LECCIONES DEL PADRE DE LA RETÓRICA | C62: 9786313005895 | D62: 37400 | F62: =E62*D62 -> 0
A63: EMILY BRONTË | B63: CUMBRES BORRASCOSAS | C63: 9786313006083 | D63: 19800 | F63: =E63*D63 -> 0
A64: PENELOPE SKY | B64: EL VERDUGO | C64: 9786313006076 | D64: 42000 | F64: =E64*D64 -> 0
A65: KATE FAGAN | B65: LAS TRES VIDAS DE CATE KAY | C65: 9786313005932 | D65: 43000 | F65: =E65*D65 -> 0
A66: PATRICIA STRAUCH | B66: KIARA FROST, UN CAMPAMENTO INOLVIDABLE | C66: 9786313006144 | D66: 20900 | F66: =E66*D66 -> 0
A67: LIBROS PARA COLOREAR
A68: S/D | B68: LIFE COLOREANDING | C68: 9789877470178 | D68: 17100 | F68: =E68*D68 -> 0
A69: S/D | B69: MEXICO COLOREANDING | C69: 9789877470161 | D69: 17100 | F69: =E69*D69 -> 0
A70: S/D | B70: COLOREANDING LETTERING | C70: 9789877474305 | D70: 17100 | F70: =E70*D70 -> 0
A71: S/D | B71: POSITIVO COLOREANDING | C71: 9789877471779 | D71: 17100 | F71: =E71*D71 -> 0
A72: Helen H Wu | B72: CAPI CUDDLES - LIBRO PARA COLOREAR | C72: 9786313005178 | D72: 15600 | F72: =E72*D72 -> 0
A73: Helen H Wu | B73: CAPI HOLIDAYS - LIBRO PARA COLOREAR | C73: 9786313005161 | D73: 15600 | F73: =E73*D73 -> 0
A74: Gale & Jull | B74: COLOREANDING DULCE NAVIDAD | C74: 9786313004874 | D74: 17100 | F74: =E74*D74 -> 0
A75: S/D | B75: COLOREANDING TATOO | C75: 9786078614462 | D75: 17100 | F75: =E75*D75 -> 0
A76: S/D | B76: COLOREANDING CACTUS Y SUCULENTAS | C76: 9786078614691 | D76: 17100 | F76: =E76*D76 -> 0
A77: S/D | B77: COLOREANDING FENG SHUI | C77: 9786078712748 | D77: 17100 | F77: =E77*D77 -> 0
A78: S/D | B78: COLOREANDING GIRL POWER | C78: 9789877478082 | D78: 17100 | F78: =E78*D78 -> 0
A79: S/D | B79: LETTERING DESDE CERO | C79: 9786313001279 | D79: 17100 | F79: =E79*D79 -> 0
... A104: S/D | B104: TAROT PARA COLOREAR | C104: 9786313001170 | D104: 20900 | F104: =E104*D104 -> 0
A105: Ficción Juvenil
A106: ALICE OSEMAN | B106: HEARTSTOPPER | C106: 9789877475876 | D106: 31000 | F106: =E106*D106 -> 0
A107: ALICE OSEMAN | B107: HEARTSTOPPER 2 | C107: 9789877476583 | D107: 31000 | F107: =E107*D107 -> 0
A108: ALICE OSEMAN | B108: HEARTSTOPPER 3 | C108: 9789877476972 | D108: 31000 | F108: =E108*D108 -> 0
A109: ALICE OSEMAN | B109: HEARTSTOPPER 4 | C109: 9789877477474 | D109: 31000 | F109: =E109*D109 -> 0
A110: ALICE OSEMAN | B110: HEARTSTOPPER 5 | C110: 9786313001002 | D110: 31000 | F110: =E110*D110 -> 0
A111: ALICE OSEMAN | B111: HEARTSTOPPER - UNA SERIE DE NETFLIX | C111: 9789877478433 | D111: 31000 | F111: =E111*D111 -> 0
A112: ALICE OSEMAN | B112: HEARTSTOPPER: EDICIÓN ESPECIAL - TOMO 1 | C112: 9786313000319 | D112: 41800 | F112: =E112*D112 -> 0
A113: ALICE OSEMAN | B113: HEARTSTOPPER: EDICIÓN ESPECIAL - TOMO 2 | C113: 9786313000326 | D113: 41800 | F113: =E113*D113 -> 0
A114: ALICE OSEMAN | B114: HEARTSTOPPER: EDICIÓN ESPECIAL - TOMO 3 | C114: 9786313000340 | D114: 41800 | F114: =E114*D114 -> 0
A115: ALICE OSEMAN | B115: HEARTSTOPPER: EDICIÓN ESPECIAL - TOMO 4 | C115: 9786313000470 | D115: 41800 | F115: =E115*D115 -> 0
A116: ALICE OSEMAN | B116: PACK HEARTSTOPPER | C116: 9789877478501 | D116: 99000 | F116: =E116*D116 -> 0
A117: ALICE OSEMAN | B117: HEARTSTOPPER PARA COLOREAR | C117: 9789877477573 | D117: 25300 | F117: =E117*D117 -> 0
... A307: RODRIGO H. VILA | B307: MENGELE. EN EL NOMBRE DEL PADRE | C307: 9786313003242 | D307: 41800 | F307: =E307*D307 -> 0
A308: NOVELA ROMANTICA
A309: MARIANO CATTANEO | B309: NO HAY VERANO PARA LOS MUERTOS | C309: 9786313003112 | D309: 33600 | F309: =E309*D309 -> 0
A310: SIMONE SOLTANI | B310: CRUZAR LA LÍNEA | C310: 9786313003198 | D310: 41800 | F310: =E310*D310 -> 0
A311: KAREN DELORBE | B311: UN MINUTO ANTES DEL AMANECER | C311: 9786313003044 | D311: 38000 | F311: =E311*D311 -> 0
A312: ARACELI SAMUDIO | B312: MI HOGAR ERES TÚ | C312: 9786313003181 | D312: 39600 | F312: =E312*D312 -> 0
A313: James, Amy | B313: CINCO LETRAS PARA DECIR AMOR. | C313: 9786313004669 | D313: 42000 | F313: =E313*D313 -> 0
A314: Fratino, Maximiliano | B314: 8 hilos : desandando el camino | C314: 9786313002856 | D314: 35200 | F314: =E314*D314 -> 0
A315: Harwood, Eli | B315: Seguro es amor | C315: 9786313001521 | D315: 30800 | F315: =E315*D315 -> 0
A316: LAURA G. MIRANDA | B316: ELLOS | C316: 9786313003464 | D316: 38000 | F316: =E316*D316 -> 0
A317: LAURA G. MIRANDA | B317: VOLVER A MI | C317: 9789877475241 | D317: 37400 | F317: =E317*D317 -> 0
A318: LAURA G. MIRANDA | B318: DESPUES DEL ABISMO | C318: 9789877475845 | D318: 37400 | F318: =E318*D318 -> 0
A319: Mila Kate | B319: ENTRE TÙ Y YO | C319: 9786313003877 | D319: 44000 | F319: =E319*D319 -> 0
A320: Shen, L.J.Parker S. Huntington | B320: MI OSCURO DESEO | C320: 9786313004195 | D320: 46000 | F320: =E320*D320 -> 0
... A388: GRACIELA RAMOS | B388: LA BOCA ROJA DEL RIACHUELO: EL AMOR EN LA DESIGUALDAD | C388: 9786313002757 | D388: 40700 | F388: =E388*D388 -> 0
A389: Ficción
A390: De Zan, Guillermo | B390: POR AMOR AL CLAN : HONRA A QUIENES VIVIERON ANTES QUE VOS Y DESATA LOS NUDOS QUE TE ATAN AL PASADO. | C390: 9786313004713 | D390: 33000 | F390: =E390*D390 -> 0
A391: Walters, Milena | B391: AMOR EN JUEGO : CRUZAR LA LÍNEA | C391: 9786313004737 | D391: 45100 | F391: =E391*D391 -> 0
...

Sheet Otras
A1: Autor | B1: Nombre | C1: ISBN | D1: Precio | E1: Cant. | F1: Subtotal
A2: MARVEL - LA HISTORIA VISUAL
A3: MARVEL LA HISTORIA VISUAL | B3: 1939 A 1949 EN LOS PRINCIPIOS | C3: 9780241388136 | D3: 5000 | F3: =E3*D3 -> 0
A4: MARVEL LA HISTORIA VISUAL | B4: 1950 A 1959 LOS VIENTOS DE CAMBIO | C4: 9780241388143 | D4: 5000 | F4: =E4*D4 -> 0
A5: MARVEL LA HISTORIA VISUAL | B5: 1960 A 1964 EL RENACER DEL SUPERHÉROE | C5: 9780241388150 | D5: 5000 | F5: =E5*D5 -> 0
A6: MARVEL LA HISTORIA VISUAL | B6: 1965 A 1969 MARVEL EN LA CULTURA COMERCIAL | C6: 9780241388198 | D6: 5000 | F6: =E6*D6 -> 0
A7: MARVEL LA HISTORIA VISUAL | B7: 1970 A 1979 HACIENDO HISTORIA | C7: 9780241388204 | D7: 5000 | F7: =E7*D7 -> 0
A8: MARVEL LA HISTORIA VISUAL | B8: 1980 A 1984 UN UNIVERSO EN EVOLUCIÓN | C8: 9780241388211 | D8: 5000 | F8: =E8*D8 -> 0
A9: MARVEL LA HISTORIA VISUAL | B9: 1985 A 1989 EMPIEZA UN NUEVO ORDEN | C9: 9780241388228 | D9: 5000 | F9: =E9*D9 -> 0
A10: MARVEL LA HISTORIA VISUAL | B10: 1990 A 1994 ARTISTAS ESTRELLA | C10: 9780241388235 | D10: 5000 | F10: =E10*D10 -> 0
A11: MARVEL LA HISTORIA VISUAL | B11: 1995 A 1999 NUEVOS COMIENZOS | C11: 9780241388259 | D11: 5000 | F11: =E11*D11 -> 0
A12: MARVEL LA HISTORIA VISUAL | B12: 2000 A 2004 CAMINO DE HOLLYWOOD | C12: 9780241388266 | D12: 5000 | F12: =E12*D12 -> 0
A13: MARVEL LA HISTORIA VISUAL | B13: 2005 A 2009 MARVEL VA A LA GUERRA | C13: 9780241388273 | D13: 5000 | F13: =E13*D13 -> 0
A14: MARVEL LA HISTORIA VISUAL | B14: 2010 a 2019 LA ERA DE LOS HÉROES | C14: 9780241388280 | D14: 5000 | F14: =E14*D14 -> 0
A15: STAR WARS - LA HISTORIA VISUAL
A16: STAR WARS LA HISTORIA VISUAL | B16: 1: LA VIDA ANTES DE STAR WARS Y UNA NUEVA ESPERANZA | C16: 9780241554463 | D16: 5000 | F16: =E16*D16 -> 0
A17: STAR WARS LA HISTORIA VISUAL | B17: 2: CONTINÚA LA TRILOGÍA ORIGINAL | C17: 9780241553817 | D17: 5000 | F17: =E17*D17 -> 0
A18: STAR WARS LA HISTORIA VISUAL | B18: 3: MÁS ALLÁ DEL CINE | C18: 9780241553824 | D18: 5000 | F18: =E18*D18 -> 0
A19: STAR WARS LA HISTORIA VISUAL | B19: 4: LA TRILOGÍA DE LAS PRECUELAS 1ERA PARTE | C19: 9780241553831 | D19: 5000 | F19: =E19*D19 -> 0
A20: STAR WARS LA HISTORIA VISUAL | B20: 5: LA TRILOGÍA DE LAS PRECUELAS SEGUNDA PARTE | C20: 9780241553848 | D20: 5000 | F20: =E20*D20 -> 0
A21: STAR WARS LA HISTORIA VISUAL | B21: 6: DE LAS GUERRAS DE LOS CLONES EN ADELANTE | C21: 9780241553855 | D21: 5000 | F21: =E21*D21 -> 0
A22: STAR WARS LA HISTORIA VISUAL | B22: 7: UNA NUEVA ERA Y EL DESPERTAR DE LA FUERZA | C22: 9780241553862 | D22: 5000 | F22: =E22*D22 -> 0
A23: STAR WARS LA HISTORIA VISUAL | B23: 8: CONTINÚA LA TRILOGÍA DE SECUELAS - EL FUTURO DE LA SAGA | C23: 9780241553879 | D23: 5000 | F23: =E23*D23 -> 0
A24: BATMAN - LA HISTORIA VISUAL
A25: BATMAN LA HISTORIA VISUAL | B25: EL CABALLERO OSCURO 1930-1940 | C25: 9780241419519 | D25: 5000 | F25: =E25*D25 -> 0
A26: BATMAN LA HISTORIA VISUAL | B26: UNA NUEVA DIMENSIÓN 1950 | C26: 9780241419526 | D26: 5000 | F26: =E26*D26 -> 0
A27: BATMAN LA HISTORIA VISUAL | B27: EL CRUZADO DE LA CAPA 1960 | C27: 9780241419540 | D27: 5000 | F27: =E27*D27 -> 0
A28: BATMAN LA HISTORIA VISUAL | B28: UN CABALLERO MAS OSCURO 1970 | C28: 9780241419557 | D28: 5000 | F28: =E28*D28 -> 0
A29: BATMAN LA HISTORIA VISUAL | B29: EL REGRESO DEL CABALLERO OSCURO 1980 | C29: 9780241419571 | D29: 5000 | F29: =E29*D29 -> 0
A30: BATMAN LA HISTORIA VISUAL | B30: LA SOMBRA DEL MURCIÉLAGO 1990 | C30: 9780241419588 | D30: 5000 | F30: =E30*D30 -> 0
A31: BATMAN LA HISTORIA VISUAL | B31: BATMAN Y ROBIN RENACIDOS 2000 | C31: 9780241419595 | D31: 5000 | F31: =E31*D31 -> 0
A32: BATMAN LA HISTORIA VISUAL | B32: UNA NUEVA LEYENDA 2010 | C32: 9780241419601 | D32: 5000 | F32: =E32*D32 -> 0
A33: ARTEMISA - ELIGE TU PROPIA AVENTURA
A34: R. A. Montgomery | B34: EL ESPACIO Y MAS ALLA-1 | C34: 9789876748544 | D34: 16900 | F34: =E34*D34 -> 0
A35: R. A. Montgomery | B35: VIAJE BAJO EL MAR-2 | C35: 9789876748513 | D35: 16900 | F35: =E35*D35 -> 0
A36: R. A. Montgomery | B36: REGRESO A LA ATLANTIDA-3 | C36: 9789876748520 | D36: 16900 | F36: =E36*D36 -> 0
A37: R. A. Montgomery | B37: EL ABOMINABLE HOMBRE DE LA NIEVE-4 | C37: 9789876748506 | D37: 16900 | F37: =E37*D37 -> 0
A38: Deborah Lerme Goodman | B38: LA MAGIA DEL UNICORNIO-5 | C38: 9789876748568 | D38: 16900 | F38: =E38*D38 -> 0
A39: R. A. Montgomery | B39: LA CASA DEL PELIGRO-6 | C39: 9789876748537 | D39: 16900 | F39: =E39*D39 -> 0
A40: R. A. Montgomery | B40: LA BRILLANTE DRA WOGAN-7 | C40: 9789876748575 | D40: 16900 | F40: =E40*D40 -> 0
A41: R. A. Montgomery | B41: PERDIDOS EN EL AMAZONAS-8 | C41: 9789876748582 | D41: 16900 | F41: =E41*D41 -> 0
A42: Jim Becket | B42: EL ORO DE LOS INCAS-10 | C42: 9789876748599 | D42: 16900 | F42: =E42*D42 -> 0
A43: D. Terman | B43: EN GLOBO AL SAHARA-9 | C43: 9789876748605 | D43: 16900 | F43: =E43*D43 -> 0
A44: R. A. Montgomery | B44: SANGRE EN LA DAGA-11 | C44: 9789876748643 | D44: 16900 | F44: =E44*D44 -> 0
A45: Deborah Lerme Goodman | B45: EL TRONO DE ZEUS-12 | C45: 9789876748636 | D45: 16900 | F45: =E45*D45 -> 0
A46: Deborah Lerme Goodman | B46: LA TROMPETA DEL TERROR -13- | C46: 9789876748766 | D46: 16900 | F46: =E46*D46 -> 0
A47: Ken Mc-Murray | B47: ZOMBIE-14- | C47: 9789876748773 | D47: 16900 | F47: =E47*D47 -> 0
A48: Deborah Lerme Goodman | B48: ESCAPE DEL ALMACEN EMBRUJADO-15 | C48: 9789876748810 | D48: 16900 | F48: =E48*D48 -> 0
A49: Ken Mc-Murray | B49: LA MANSION DE LAS BRUJAS-16 | C49: 9789876748827 | D49: 16900 | F49: =E49*D49 -> 0
A50: Liz Windover | B50: LA ISLA SANGRIENTA-17 | C50: 9789876749091 | D50: 16900 | F50: =E50*D50 -> 0
A51: R. A. Montgomery | B51: LA ISLA DEL TIEMPO-18 | C51: 9789876749084 | D51: 16900 | F51: =E51*D51 -> 0
A52: Shannon Guilligan | B52: EL CASO DEL REY DE LA SEDA-19 | C52: 9789876749183 | D52: 16900 | F52: =E52*D52 -> 0
A53: R. A. Montgomery | B53: EL AMO DEL PODER MALIGNO -20 | C53: 9789876749190 | D53: 16900 | F53: =E53*D53 -> 0
A54: R. A. Montgomery | B54: COPA DE MUERTE-21 | C54: 9789876749282 | D54: 16900 | F54: =E54*D54 -> 0
A55: Shannon Guilligan | B55: MISION CONTRAATAQUE-22 | C55: 9789876749275 | D55: 16900 | F55: =E55*D55 -> 0
A56: Lili Simonson | B56: ANTARTIDA 23 | C56: 9789876749602 | D56: 16900 | F56: =E56*D56 -> 0
A57: Deborah Lerme Goodman | B57: EL VUELO DEL UNICORNIO -24 | C57: 9789876749732 | D57: 16900 | F57: =E57*D57 -> 0
A58: Wilhelm Dog | B58: LA MALDICION DE LA NIEBLA PIRATA-25 | C58: 9786316549389 | D58: 16900 | F58: =E58*D58 -> 0
A59: Wilhelm Dog | B59: DRAGON CHINO-26 | C59: 9786316549396 | D59: 16900 | F59: =E59*D59 -> 0
A60: ELIGE TU PROPIA AVENTURA - TAPA DURA
A61: Wilhelm Dog | B61: La Maldicion de la Niebla Pirata-25 Tapa Dura | C61: 9786316549419 | D61: 16500 | F61: =E61*D61 -> 0
A62: Wilhelm Dog | B62: Dragon Chino-26-Novedad- Tapa Dura | C62: 9786316549402 | D62: 16500 | F62: =E62*D62 -> 0
A63: ELIGE TU PROPIA AVENTRA - EN INGLÉS
A64: Ken Mc-Murray | B64: Zombie | C64: 9786316549495 | D64: 16500 | F64: =E64*D64 -> 0
A65: Deborah Lerme Goodman | B65: The Flight Of The Unicorns | C65: 9786316549488 | D65: 16500 | F65: =E65*D65 -> 0
A67: TRISKELION
A68: ROBIN WOOD | B68: DRÁCULA | C68: 978-631-91262-0-4 | D68: 20000 | F68: =E68*D68 -> 0 | G68: NOVEDAD
A70: HISTORIETECA
A71: Hor Lang | B71: EL PEQUEÑO TIMY ¡SALE DE CASA! | C71: 9786319041774 | D71: 16000 | F71: =E71*D71 -> 0 | G71: NOVEDAD
A72: Hor Lang | B72: EL PEQUEÑO TIMY | C72: 9789874800749 | D72: 14000 | F72: =E72*D72 -> 0
A73: CARLOS TRILLO Y EDUARDO RISSO | B73: CUENTOS DE TERROR | C73: 9789874800732 | D73: 14500 | F73: =E73*D73 -> 0
A75: GUADAL
A76: Equipo Editorial Guadal | B76: AVATAR THE LAST AIRBENDER: LA BUSQUEDA 01 | C76: 9789871713974 | D76: 9999 | F76: =E76*D76 -> 0 | G76: 40% DESCUENTO
A77: Equipo Editorial Guadal | B77: AVATAR THE LAST AIRBENDER: LA BUSQUEDA 02 | C77: 9789871713981 | D77: 9999 | F77: =E77*D77 -> 0 | G77: 40% DESCUENTO
A78: Equipo Editorial Guadal | B78: AVATAR THE LAST AIRBENDER: LA BUSQUEDA 03 | C78: 9789871713998 | D78: 9999 | F78: =E78*D78 -> 0 | G78: 40% DESCUENTO
A79: Equipo Editorial Guadal | B79: AVATAR THE LAST AIRBENDER COLOREA CON EL MAESTRO DEL AIRE | C79: 9789871713806 | D79: 12999 | F79: =E79*D79 -> 0 | G79: 40% DESCUENTO
A80: Equipo Editorial Guadal | B80: AVATAR THE LAST AIRBENDER: LA PROMESA 01 | C80: 9789871713813 | D80: 9999 | F80: =E80*D80 -> 0 | G80: 40% DESCUENTO
A81: Equipo Editorial Guadal | B81: AVATAR THE LAST AIRBENDER: LA PROMESA 02 | C81: 9789871713820 | D81: 9999 | F81: =E81*D81 -> 0 | G81: 40% DESCUENTO
A82: Equipo Editorial Guadal | B82: AVATAR THE LAST AIRBENDER: LA PROMESA 03 | C82: 9789871713837 | D82: 9999 | F82: =E82*D82 -> 0 | G82: 40% DESCUENTO
A84: SECTOR EDITORIAL
A85: VARIOS AUTORES | B85: BRECCIA NEGRO - EDICION DEFINITIVA | C85: 9786319039528 | D85: 20000 | F85: =E85*D85 -> 0
A86: BRECCIA, TRILLO | B86: BUSCAVIDAS | C86: 9786319039511 | D86: 15000 | F86: =E86*D86 -> 0
A87: Jorge Gonzalez | B87: DEAR PATAGONIA | C87: 9786319039504 | D87: 30000 | F87: =E87*D87 -> 0
A88: Mario Rulloni, Pablo Zweig | B88: LIVINGSTONE AMAZONIA + VIDEO STAR | C88: 9789874907363 | D88: 20000 | F88: =E88*D88 -> 0
A89: Leopoldo Durañona | B89: SOY UN COBARDE Y OTRAS HISTORIAS | C89: 9786319039535 | D89: 20000 | F89: =E89*D89 -> 0
A91: MERCI
A92: ISBN | B92: Nombre | D92: Precio | E92: Cant. | F92: Subtotal
A93: Matt Kindt/David Rubin | B93: Ether Vol. 1: La Muerte de la Última Llama Dorada | C93: 9789874898005 | D93: 10500 | F93: =E93*D93 -> 0
A94: Guido Barsi/Lele Lou | B94: Entre Tinieblas NOVEDAD | C94: 9789874898012 | D94: 4900 | F94: =E94*D94 -> 0
A96: KEMURI
A97: SHINGO HONDA | B97: HAPPYLAND | C97: 9786319127973 | D97: 18000 | F97: =E97*D97 -> 0 | G97: SALIDA RETRASADA
A98: PEYO | B98: BOY MEETS MARIA | C98: 9789874808264 | D98: 15000 | E98: 1 | F98: =E98*D98 -> 0 | G98: REIMPRESION
A99: COMAKU | B99: ¿MI HOBBY ES RARO? | C99: 9789874887375 | D99: 14000 | F99: =E99*D99 -> 0
A100: MORI MOYORI | B100: ABRAZANDO TU NOCHE | C100: 9786319073355 | D100: 14000 | E100: 2 | F100: =E100*D100 -> 0
A101: Saikomic | B101: ANTAGONISTA 1 | C101: 9789874808202 | D101: 14000 | F101: =E101*D101 -> 0
A102: Saikomic | B102: ANTAGONISTA 3 | C102: 9789874887368 | D102: 14000 | F102: =E102*D102 -> 0
A103: Saikomic | B103: ANTAGONISTA 4 | C103: 9786319073324 | D103: 14000 | F103: =E103*D103 -> 0
A104: SETO YUKI | B104: CHITOSE | C104: 9786319127973 | D104: 17000 | F104: =E104*D104 -> 0
A105: Akira Nakata | B105: DEMASIADO CERCA PARA ENAMORARSE | C105: 9786319073300 | D105: 14000 | F105: =E105*D105 -> 0
A106: SHUHO SATO | B106: GIVE MY REGARDS TO BLACK JACK 01 | C106: 9789874808219 | D106: 18000 | F106: =E106*D106 -> 0
...

Sheet Merchandising
A2: PRODUCTO | B2: ISBN | C2: Precio | D2: Cantidad | E2: Subotal
A3: BANDANA KONOHA NARUTO | B3: S/D | C3: 1250 | E3: =D3*C3 -> 0
A4: BANDANA TACHADA NARUTO | B4: S/D | C4: 1250 | E4: =D4*C4 -> 0
A5: BANDANA KONOHA AZUL NARUTO | B5: S/D | C5: 1250 | E5: =D5*C5 -> 0
A6: KUNAI NARUTO | B6: S/D | C6: 1100 | E6: =D6*C6 -> 0
A7: SHURIKEN NARUTO | B7: S/D | C7: 1100 | E7: =D7*C7 -> 0
A8: CUCHILLAS NARUTO | B8: S/D | C8: 1100 | E8: =D8*C8 -> 0
A9: LIBRETA DEATH NOTE | B9: S/D | C9: 6000 | E9: =D9*C9 -> 0
A10: VASOS DE PLÁSTICO ANIME (CONSULTA MODELOS) | B10: S/D | C10: 800 | E10: =D10*C10 -> 0
A11: ANTEOJOS MEME PIXEL | B11: S/D | C11: 3000 | E11: =D11*C11 -> 0 | F11: 15% DESCUENTO LLEVANDO 50 UNIDADES O MAS
A12: MOCHILA SAKURA DE CUERO SINTÉTICO | B12: S/D | C12: 28000 | E12: =D12*C12 -> 0 | F12: 15% DESCUENTO LLEVANDO 50 UNIDADES O MAS
A13: PACK ESFERAS DEL DRAGON 7 ESFERAS 4CM | B13: S/D | C13: 28000 | E13: =D13*C13 -> 0
A14: ESFERA DEL DRAGON 4 ESTRELLAS GRANDE 10CM | B14: S/D | C14: 25500 | E14: =D14*C14 -> 0 | F14: 15% DESCUENTO LLEVANDO 50 UNIDADES O MAS
A15: ESFERA DEL DRAGÓN 4 ESTRELLAS LLAVERO 4CM | B15: S/D | C15: 3000 | E15: =D15*C15 -> 0 | F15: 15% DESCUENTO LLEVANDO 50 UNIDADES O MAS
A16: CARTAS CLOW SAKURA EN CAJA DE CARTON | B16: S/D | C16: 13000 | E16: =D16*C16 -> 0
A17: CARTAS CLOW SAKURA ROSA EN CAJA DE CARTON | B17: S/D | C17: 13000 | E17: =D17*C17 -> 0
A18: CARTAS CLOW SAKURA CLEAR CARD ARC | B18: S/D | C18: 13000 | E18: =D18*C18 -> 0
A19: CORBATA HARRY POTTER GRYFFINDOR | B19: S/D | C19: 5000 | E19: =D19*C19 -> 0
A20: CORBATA HARRY POTTER SLYTHERIN | B20: S/D | C20: 5000 | E20: =D20*C20 -> 0
A21: CORBATA HARRY POTTER HUFFLEPUFF | B21: S/D | C21: 5000 | E21: =D21*C21 -> 0
A22: CORBATA HARRY POTTER RAVENCLAW | B22: S/D | C22: 5000 | E22: =D22*C22 -> 0
A23: MONEDERO SAPO NARUTO | B23: S/D | C23: 4000 | E23: =D23*C23 -> 0 | F23: 15% DESCUENTO LLEVANDO 50 UNIDADES O MAS
A24: COLGANTE GIRATIEMPOS HARRY POTTER | B24: S/D | C24: 3000 | E24: =D24*C24 -> 0 | F24: 15% DESCUENTO LLEVANDO 50 UNIDADES O MAS
A25: LENTES HARRY POTTER | B25: S/D | C25: 3000 | E25: =D25*C25 -> 0 | F25: 15% DESCUENTO LLEVANDO 50 UNIDADES O MAS
A26: CAJA MUSICAL MI VECINO TOTORO | B26: S/D | C26: 9500 | E26: =D26*C26 -> 0
A27: CAJA MUSICAL EL VIAJE DE CHIHIRO | B27: S/D | C27: 9500 | E27: =D27*C27 -> 0
A28: CAJA MUSICAL SAILOR MOON ROSA MODELO 2 | B28: S/D | C28: 9500 | E28: =D28*C28 -> 0
A29: CAJA MUSICAL HARRY POTTER ORDEN DEL FENIX | B29: S/D | C29: 9500 | E29: =D29*C29 -> 0
A30: CAJA MUSICAL HARRY POTTER 9 3/4 ROJA | B30: S/D | C30: 9500 | E30: =D30*C30 -> 0
A31: CAJA MUSICAL MICHAEL JACKSON | B31: S/D | C31: 9500 | E31: =D31*C31 -> 0
A32: CAJA MUSICAL ATTACK ON TITAN | B32: S/D | C32: 9500 | E32: =D32*C32 -> 0
A33: CAJA MUSICAL SAILOR MOON (MODELO EN NEGRO O ROSA) | B33: S/D | C33: 9500 | E33: =D33*C33 -> 0
A34: CAJA MUSICAL DEMON SLAYER | B34: S/D | C34: 9500 | E34: =D34*C34 -> 0
A35: CAJA MUSICAL JURASSIC PARK | B35: S/D | C35: 9500 | E35: =D35*C35 -> 0
A36: CAJA MUSICAL DRAGON BALL | B36: S/D | C36: 9500 | E36: =D36*C36 -> 0
A37: CAJA MUSICAL ZELDA | B37: S/D | C37: 9500 | E37: =D37*C37 -> 0
... A77: LAMPARA LED UNICORNIO SILICONA | B77: S/D | C77: 25000 | E77: =D77*C77 -> 0
A78: LAMPARA VELADOR MARIO SIGNO PREGUNTA | B78: 6986764008862 | C78: 16000 | E78: =D78*C78 -> 0
A79: LAMPARA VELADOR MARIO HONGO VERDE | B79: 5055964714215 | C79: 16000 | E79: =D79*C79 -> 0
A80: LAMPARA VELADOR MARIO HONGO ROJO | B80: 5055964714215 | C80: 16000 | E80: =D80*C80 -> 0
A81: MUÑECO SORPRESA LABUBU EN CAJA 15CMS | B81: S/D | C81: 13000 | E81: =D81*C81 -> 0
A82: LLAVERO IMPRESIÓN 3D BRAINRODS TUNG TUNG SAHUR | B82: S/D | C82: 4000 | E82: =D82*C82 -> 0
A83: LLAVERO IMPRESIÓN 3D BRAINRODS TRALALELO TRALALA | B83: S/D | C83: 7000 | E83: =D83*C83 -> 0
A84: FIGURA IMPRESIÓN 3D TUNG TUNG SAHUR | B84: S/D | C84: 8500 | E84: =D84*C84 -> 0
A85: FIGURA IMPRESIÓN 3D BAILARINA CAPUCCINA | B85: S/D | C85: 10500 | E85: =D85*C85 -> 0
A86: FIGURA OFICIAL CARNIVAL TOYS SONIC 12CMS | B86: 7450122120750 | C86: 14000 | E86: =D86*C86 -> 0 | F86: NOVEDAD | G86: ORIGINALES - IVA INCLUIDO
A87: FIGURA OFICIAL CARNIVAL TOYS SONIC TAILS 12CMS | B87: 7450122120804 | C87: 14000 | E87: =D87*C87 -> 0 | F87: NOVEDAD
A88: FIGURA OFICIAL CARNIVAL TOYS SONIC KNUCKLES 12CMS | B88: 7450122120767 | C88: 14000 | E88: =D88*C88 -> 0 | F88: NOVEDAD
A89: FIGURA OFICIAL CARNIVAL TOYS SONIC AMY ROSE 12CMS | B89: 7450122120774 | C89: 14000 | E89: =D89*C89 -> 0 | F89: NOVEDAD
A90: FIGURA OFICIAL CARNIVAL TOYS SONIC DR EGGMAN 12CMS | B90: 7450122126349 | C90: 14000 | E90: =D90*C90 -> 0 | F90: NOVEDAD
A91: FIGURA OFICIAL CARNIVAL TOYS SONIC 17CMS | B91: 7450122120811 | C91: 19000 | E91: =D91*C91 -> 0 | F91: NOVEDAD
A92: CARNIVAL - FIGURA DE ACCION 50cm MARVEL SPIDERMAN | B92: 7450122049822 | C92: 62000 | E92: =D92*C92 -> 0 | F92: NOVEDAD
A93: CARNIVAL - FIGURA DE ACCION 50cm MARVEL CAPITAN AMERICA | B93: 7450122049839 | C93: 62000 | E93: =D93*C93 -> 0 | F93: NOVEDAD
A94: CARNIVAL - FIGURA DE ACCION 50cm MARVEL HULK | B94: 7450122049846 | C94: 62000 | E94: =D94*C94 -> 0 | F94: NOVEDAD
A95: CARNIVAL - FIGURA DE ACCION 50cm MARVELIRON MAN | B95: 7450122049853 | C95: 62000 | E95: =D95*C95 -> 0 | F95: NOVEDAD
A96: CARNIVAL - FIGURA DE ACCION 50cm MARVELSPIDERMAN NEGRO | B96: 7450122128558 | C96: 62000 | E96: =D96*C96 -> 0 | F96: NOVEDAD
A97: CARNIVAL - FIGURA DE ACCION 50cm MARVEL THOR | B97: 7450122128572 | C97: 62000 | E97: =D97*C97 -> 0 | F97: NOVEDAD
A98: CARNIVAL - FIGURA 23cm DC BATMAN ORIGIN | B98: 7450217044190 | C98: 16500 | E98: =D98*C98 -> 0 | F98: NOVEDAD
... A100: CARNIVAL - FIGURA 23cm DC SUPERMAN ORIGIN | B100: 7450217044213 | C100: 16500 | E100: =D100*C100 -> 0 | F100: NOVEDAD
A101: JADA - SET X 3 AUTOS ESCALA 1:64 FAST & FURIOUS NANO HOLLYWOOD RIDES - EN BLISTER | B101: 801310311233 | C101: 18500 | E101: =D101*C101 -> 0 | F101: NOVEDAD
A102: JADA - SET X 3 AUTOS ESCALA 1:64 TRASFORMERS NANO HOLLYWOOD RIDES - EN BLISTER | B102: 801310311257 | C102: 18500 | E102: =D102*C102 -> 0 | F102: NOVEDAD
A103: JADA - SET X 3 AUTOS ESCALA 1:64 BATMAN NANO HOLLYWOOD RIDES - EN BLISTER | B103: 801310319888 | C103: 18500 | E103: =D103*C103 -> 0 | F103: NOVEDAD
A104: JADA - SET X 2 AUTOS ESCALA 1:64 HARRY POTTER NANO HOLLYWOOD RIDES - EN BLISTER | B104: 801310317198 | C104: 18500 | E104: =D104*C104 -> 0 | F104: NOVEDAD
A105: JADA - AUTO ESCALA 1:32 BATMOBILE 1966 CLASSIC CON FIGURA DE BATMAN 4cm - EN CAJA | B105: 801310317037 | C105: 27500 | E105: =D105*C105 -> 0 | F105: NOVEDAD
A106: JADA - AUTO ESCALA 1:32 BATMOBILE 1989 CLASSIC CON FIGURA DE BATMAN 4cm - EN CAJA | B106: 801310317044 | C106: 27500 | E106: =D106*C106 -> 0 | F106: NOVEDAD
A107: JADA - AUTO ESCALA 1:24 BATMOBILE 1966 CLASSIC CON FIGURA DE BATMAN & ROBIN 6cm - EN CAJA | B107: 801310982594 | C107: 66000 | E107: =D107*C107 -> 0 | F107: NOVEDAD
A108: JADA - AUTO ESCALA 1:24 BATMOBILE 1989 CON FIGURA DE BATMAN 6cm - EN CAJA | B108: 801310982600 | C108: 62000 | E108: =D108*C108 -> 0 | F108: NOVEDAD
A109: JADA - AUTO ESCALA 1:24 BATMOBILE BATMAN FOREVER 1995 CON FIGURA DE BATMAN 6cm - EN CAJA | B109: 801310980361 | C109: 62000 | E109: =D109*C109 -> 0 | F109: NOVEDAD
A110: JADA - AUTO ESCALA 1:24 BATMOBILE THE DARK KNIGHT 2008 CON FIGURA DE BATMAN 6cm - EN CAJA | B110: 801310982617 | C110: 62000 | E110: =D110*C110 -> 0 | F110: NOVEDAD
A111: JADA - AUTO ESCALA 1:24 BATMOBILE 2022 CON FIGURA DE BATMAN 6cm - EN CAJA | B111: 801310327319 | C111: 62000 | E111: =D111*C111 -> 0 | F111: NOVEDAD
A112: JADA - AUTO ESCALA 1:32 TRASFORMERS OPTIMUS PRIME (CAMION) ROJO - EN CAJA | B112: 801310240786 | C112: 27500 | E112: =D112*C112 -> 0 | F112: NOVEDAD
... A131: BARCO EN BOTELLA SUMERGIBLE ONE PIECE THOUSAND SUNNY | B131: S/D | C131: 13000 | E131: =D131*C131 -> 0 | F131: NOVEDAD
A132: Bolsas para manga 14X18 cms con adhesivo Tamaño Tanko(100 unidades) | B132: S/D | C132: 2700 | E132: =D132*C132 -> 0
A133: Bolsas para manga 15X20 cms con adhesivo Tamaño B6 (100 unidades) | B133: S/D | C133: 3400 | E133: =D133*C133 -> 0
A134: Bolsas para manga 17X20 cms con adhesivo Tamaño tanko y b6 doble (100 unidades) | B134: S/D | C134: 4200 | E134: =D134*C134 -> 0
A135: Bolsas para manga 17.5 X 27.5 con adhesivo tamaño A5 | B135: S/D | C135: 5000 | E135: =D135*C135 -> 0
A136: Bolsas para comic 20X30 cms con adhesivo (100 unidades) | B136: S/D | C136: 5500 | E136: =D136*C136 -> 0
A138: SUBTOTAL | E138: =SUM(E3:E137) -> 0
